Workbook

Sheet Mesas
A1: MESAS DE TRABAJO POLITICA PÚBLICA DE SEGURIDAD HUMANA INTEGRAL
A2: Mesas | C2: Dirección | D2: Fecha | E2: Hora | F2: Dimensión principal (seguridad humana) | G2: Otras dimensiones | H2: Eje transversal Crisis (N° actores) | I2: Total actores | J2: Principales | K2: Secundarios | L2: Actores clave (principales) | M2: Meta de personas | N2: % de la meta total | O2: Meta máxima (+500)
A3: Mesas Territoriales | B3: Localidad Histórica y del Caribe Norte | C3: Por definir | D3: Por definir | E3: Por definir | F3: Comunitaria | G3: Personal; Económica | H3: =COUNTIFS('Detalle por mesa'!$B:$B,$B3,'Detalle por mesa'!$I:$I,"Principal")+COUNTIFS('Detalle por mesa'!$B:$B,$B3,'Detalle por mesa'!$I:$I,"Secundario") -> 3 | I3: =COUNTIF('Detalle por mesa'!$B:$B,$B3) -> 19 | J3: =COUNTIFS('Detalle por mesa'!$B:$B,$B3,'Detalle por mesa'!$G:$G,"Principal") -> 9 | K3: =COUNTIFS('Detalle por mesa'!$B:$B,$B3,'Detalle por mesa'!$G:$G,"Secundario") -> 10 | L3: Alcaldías Locales 1, 2 y 3; Instituto Distrital de Acción Comunal (IDACC); Instituto de Patrimonio y Cultura de Cartagena (IPCC); Secretaría de Participación y Desarrollo Social (SPD/UMATA) (+5 más; ver hoja Detalle) | M3: 350 | N3: =M3/$M$42 -> 0.14 | O3: ='Proyección ±500'!F24 -> 420
B4: Localidad De La Virgen y Turística | C4: Por definir | D4: Por definir | E4: Por definir | F4: Comunitaria | G4: Económica; Personal | H4: =COUNTIFS('Detalle por mesa'!$B:$B,$B4,'Detalle por mesa'!$I:$I,"Principal")+COUNTIFS('Detalle por mesa'!$B:$B,$B4,'Detalle por mesa'!$I:$I,"Secundario") -> 3 | I4: =COUNTIF('Detalle por mesa'!$B:$B,$B4) -> 18 | J4: =COUNTIFS('Detalle por mesa'!$B:$B,$B4,'Detalle por mesa'!$G:$G,"Principal") -> 7 | K4: =COUNTIFS('Detalle por mesa'!$B:$B,$B4,'Detalle por mesa'!$G:$G,"Secundario") -> 11 | L4: Alcaldías Locales 1, 2 y 3; Instituto Distrital de Acción Comunal (IDACC); Secretaría de Participación y Desarrollo Social (SPD/UMATA); Secretaría de Turismo (+3 más; ver hoja Detalle) | M4: 400 | N4: =M4/$M$42 -> 0.16 | O4: ='Proyección ±500'!F25 -> 480
B5: Localidad Industrial y de la Bahía | C5: Por definir | D5: Por definir | E5: Por definir | F5: Comunitaria | G5: Económica; Personal | H5: =COUNTIFS('Detalle por mesa'!$B:$B,$B5,'Detalle por mesa'!$I:$I,"Principal")+COUNTIFS('Detalle por mesa'!$B:$B,$B5,'Detalle por mesa'!$I:$I,"Secundario") -> 3 | I5: =COUNTIF('Detalle por mesa'!$B:$B,$B5) -> 17 | J5: =COUNTIFS('Detalle por mesa'!$B:$B,$B5,'Detalle por mesa'!$G:$G,"Principal") -> 7 | K5: =COUNTIFS('Detalle por mesa'!$B:$B,$B5,'Detalle por mesa'!$G:$G,"Secundario") -> 10 | L5: Alcaldías Locales 1, 2 y 3; Instituto Distrital de Acción Comunal (IDACC); Secretaría de Participación y Desarrollo Social (SPD/UMATA); Asociaciones de Juntas de Acción Comunal (ASOJAC) (+3 más; ver hoja Detalle) | M5: 350 | N5: =M5/$M$42 -> 0.14 | O5: ='Proyección ±500'!F26 -> 420
A7: Mesas Rurales | B7: Boquilla | C7: Por definir | D7: Por definir | E7: Por definir | F7: Comunitaria | G7: Ambiental | H7: =COUNTIFS('Detalle por mesa'!$B:$B,$B7,'Detalle por mesa'!$I:$I,"Principal")+COUNTIFS('Detalle por mesa'!$B:$B,$B7,'Detalle por mesa'!$I:$I,"Secundario") -> 4 | I7: =COUNTIF('Detalle por mesa'!$B:$B,$B7) -> 12 | J7: =COUNTIFS('Detalle por mesa'!$B:$B,$B7,'Detalle por mesa'!$G:$G,"Principal") -> 5 | K7: =COUNTIFS('Detalle por mesa'!$B:$B,$B7,'Detalle por mesa'!$G:$G,"Secundario") -> 7 | L7: Alcaldías Locales 1, 2 y 3; Instituto Distrital de Acción Comunal (IDACC); Secretaría de Participación y Desarrollo Social (SPD/UMATA); Asociaciones de Juntas de Acción Comunal (ASOJAC) (+1 más; ver hoja Detalle) | M7: 60 | N7: =M7/$M$42 -> 0.024 | O7: ='Proyección ±500'!F29 -> 75
B8: Arroyo de Piedra | C8: Por definir | D8: Por definir | E8: Por definir | F8: Comunitaria | G8: Ambiental | H8: =COUNTIFS('Detalle por mesa'!$B:$B,$B8,'Detalle por mesa'!$I:$I,"Principal")+COUNTIFS('Detalle por mesa'!$B:$B,$B8,'Detalle por mesa'!$I:$I,"Secundario") -> 4 | I8: =COUNTIF('Detalle por mesa'!$B:$B,$B8) -> 12 | J8: =COUNTIFS('Detalle por mesa'!$B:$B,$B8,'Detalle por mesa'!$G:$G,"Principal") -> 5 | K8: =COUNTIFS('Detalle por mesa'!$B:$B,$B8,'Detalle por mesa'!$G:$G,"Secundario") -> 7 | L8: Alcaldías Locales 1, 2 y 3; Instituto Distrital de Acción Comunal (IDACC); Secretaría de Participación y Desarrollo Social (SPD/UMATA); Asociaciones de Juntas de Acción Comunal (ASOJAC) (+1 más; ver hoja Detalle) | M8: 25 | N8: =M8/$M$42 -> 0.01 | O8: ='Proyección ±500'!F30 -> 25
B9: Punta Canoa | C9: Por definir | D9: Por definir | E9: Por definir | F9: Comunitaria | G9: Ambiental | H9: =COUNTIFS('Detalle por mesa'!$B:$B,$B9,'Detalle por mesa'!$I:$I,"Principal")+COUNTIFS('Detalle por mesa'!$B:$B,$B9,'Detalle por mesa'!$I:$I,"Secundario") -> 4 | I9: =COUNTIF('Detalle por mesa'!$B:$B,$B9) -> 12 | J9: =COUNTIFS('Detalle por mesa'!$B:$B,$B9,'Detalle por mesa'!$G:$G,"Principal") -> 5 | K9: =COUNTIFS('Detalle por mesa'!$B:$B,$B9,'Detalle por mesa'!$G:$G,"Secundario") -> 7 | L9: Alcaldías Locales 1, 2 y 3; Instituto Distrital de Acción Comunal (IDACC); Secretaría de Participación y Desarrollo Social (SPD/UMATA); Asociaciones de Juntas de Acción Comunal (ASOJAC) (+1 más; ver hoja Detalle) | M9: 20 | N9: =M9/$M$42 -> 0.008 | O9: ='Proyección ±500'!F31 -> 25
B10: Bayunca | C10: Por definir | D10: Por definir | E10: Por definir | F10: Comunitaria | G10: Ambiental | H10: =COUNTIFS('Detalle por mesa'!$B:$B,$B10,'Detalle por mesa'!$I:$I,"Principal")+COUNTIFS('Detalle por mesa'!$B:$B,$B10,'Detalle por mesa'!$I:$I,"Secundario") -> 3 | I10: =COUNTIF('Detalle por mesa'!$B:$B,$B10) -> 11 | J10: =COUNTIFS('Detalle por mesa'!$B:$B,$B10,'Detalle por mesa'!$G:$G,"Principal") -> 5 | K10: =COUNTIFS('Detalle por mesa'!$B:$B,$B10,'Detalle por mesa'!$G:$G,"Secundario") -> 6 | L10: Alcaldías Locales 1, 2 y 3; Instituto Distrital de Acción Comunal (IDACC); Secretaría de Participación y Desarrollo Social (SPD/UMATA); Asociaciones de Juntas de Acción Comunal (ASOJAC) (+1 más; ver hoja Detalle) | M10: 65 | N10: =M10/$M$42 -> 0.026 | O10: ='Proyección ±500'!F32 -> 90
B11: Pasacaballos | C11: Por definir | D11: Por definir | E11: Por definir | F11: Comunitaria | G11: Ambiental | H11: =COUNTIFS('Detalle por mesa'!$B:$B,$B11,'Detalle por mesa'!$I:$I,"Principal")+COUNTIFS('Detalle por mesa'!$B:$B,$B11,'Detalle por mesa'!$I:$I,"Secundario") -> 3 | I11: =COUNTIF('Detalle por mesa'!$B:$B,$B11) -> 12 | J11: =COUNTIFS('Detalle por mesa'!$B:$B,$B11,'Detalle por mesa'!$G:$G,"Principal") -> 6 | K11: =COUNTIFS('Detalle por mesa'!$B:$B,$B11,'Detalle por mesa'!$G:$G,"Secundario") -> 6 | L11: Alcaldías Locales 1, 2 y 3; Instituto Distrital de Acción Comunal (IDACC); Secretaría de Participación y Desarrollo Social (SPD/UMATA); Asociaciones de Juntas de Acción Comunal (ASOJAC) (+2 más; ver hoja Detalle) | M11: 50 | N11: =M11/$M$42 -> 0.02 | O11: ='Proyección ±500'!F33 -> 60
B12: Arroyo Grande | C12: Por definir | D12: Por definir | E12: Por definir | F12: Comunitaria | G12: Ambiental | H12: =COUNTIFS('Detalle por mesa'!$B:$B,$B12,'Detalle por mesa'!$I:$I,"Principal")+COUNTIFS('Detalle por mesa'!$B:$B,$B12,'Detalle por mesa'!$I:$I,"Secundario") -> 3 | I12: =COUNTIF('Detalle por mesa'!$B:$B,$B12) -> 11 | J12: =COUNTIFS('Detalle por mesa'!$B:$B,$B12,'Detalle por mesa'!$G:$G,"Principal") -> 5 | K12: =COUNTIFS('Detalle por mesa'!$B:$B,$B12,'Detalle por mesa'!$G:$G,"Secundario") -> 6 | L12: Alcaldías Locales 1, 2 y 3; Instituto Distrital de Acción Comunal (IDACC); Secretaría de Participación y Desarrollo Social (SPD/UMATA); Asociaciones de Juntas de Acción Comunal (ASOJAC) (+1 más; ver hoja Detalle) | M12: 25 | N12: =M12/$M$42 -> 0.01 | O12: ='Proyección ±500'!F34 -> 30
B13: Santa Ana | C13: Por definir | D13: Por definir | E13: Por definir | F13: Comunitaria | G13: Ambiental | H13: =COUNTIFS('Detalle por mesa'!$B:$B,$B13,'Detalle por mesa'!$I:$I,"Principal")+COUNTIFS('Detalle por mesa'!$B:$B,$B13,'Detalle por mesa'!$I:$I,"Secundario") -> 6 | I13: =COUNTIF('Detalle por mesa'!$B:$B,$B13) -> 16 | J13: =COUNTIFS('Detalle por mesa'!$B:$B,$B13,'Detalle por mesa'!$G:$G,"Principal") -> 6 | K13: =COUNTIFS('Detalle por mesa'!$B:$B,$B13,'Detalle por mesa'!$G:$G,"Secundario") -> 10 | L13: Alcaldías Locales 1, 2 y 3; Instituto Distrital de Acción Comunal (IDACC); Secretaría de Participación y Desarrollo Social (SPD/UMATA); Asociaciones de Juntas de Acción Comunal (ASOJAC) (+2 más; ver hoja Detalle) | M13: 30 | N13: =M13/$M$42 -> 0.012 | O13: ='Proyección ±500'!F35 -> 30
B14: Tierra bomba | C14: Por definir | D14: Por definir | E14: Por definir | F14: Comunitaria | G14: Ambiental | H14: =COUNTIFS('Detalle por mesa'!$B:$B,$B14,'Detalle por mesa'!$I:$I,"Principal")+COUNTIFS('Detalle por mesa'!$B:$B,$B14,'Detalle por mesa'!$I:$I,"Secundario") -> 6 | I14: =COUNTIF('Detalle por mesa'!$B:$B,$B14) -> 15 | J14: =COUNTIFS('Detalle por mesa'!$B:$B,$B14,'Detalle por mesa'!$G:$G,"Principal") -> 5 | K14: =COUNTIFS('Detalle por mesa'!$B:$B,$B14,'Detalle por mesa'!$G:$G,"Secundario") -> 10 | L14: Alcaldías Locales 1, 2 y 3; Instituto Distrital de Acción Comunal (IDACC); Secretaría de Participación y Desarrollo Social (SPD/UMATA); Asociaciones de Juntas de Acción Comunal (ASOJAC) (+1 más; ver hoja Detalle) | M14: 30 | N14: =M14/$M$42 -> 0.012 | O14: ='Proyección ±500'!F36 -> 35
B15: Bocachica | C15: Por definir | D15: Por definir | E15: Por definir | F15: Comunitaria | G15: Ambiental | H15: =COUNTIFS('Detalle por mesa'!$B:$B,$B15,'Detalle por mesa'!$I:$I,"Principal")+COUNTIFS('Detalle por mesa'!$B:$B,$B15,'Detalle por mesa'!$I:$I,"Secundario") -> 6 | I15: =COUNTIF('Detalle por mesa'!$B:$B,$B15) -> 15 | J15: =COUNTIFS('Detalle por mesa'!$B:$B,$B15,'Detalle por mesa'!$G:$G,"Principal") -> 5 | K15: =COUNTIFS('Detalle por mesa'!$B:$B,$B15,'Detalle por mesa'!$G:$G,"Secundario") -> 10 | L15: Alcaldías Locales 1, 2 y 3; Instituto Distrital de Acción Comunal (IDACC); Secretaría de Participación y Desarrollo Social (SPD/UMATA); Asociaciones de Juntas de Acción Comunal (ASOJAC) (+1 más; ver hoja Detalle) | M15: 30 | N15: =M15/$M$42 -> 0.012 | O15: ='Proyección ±500'!F37 -> 35
B16: Isla del Rosario | C16: Por definir | D16: Por definir | E16: Por definir | F16: Comunitaria | G16: Ambiental | H16: =COUNTIFS('Detalle por mesa'!$B:$B,$B16,'Detalle por mesa'!$I:$I,"Principal")+COUNTIFS('Detalle por mesa'!$B:$B,$B16,'Detalle por mesa'!$I:$I,"Secundario") -> 6 | I16: =COUNTIF('Detalle por mesa'!$B:$B,$B16) -> 15 | J16: =COUNTIFS('Detalle por mesa'!$B:$B,$B16,'Detalle por mesa'!$G:$G,"Principal") -> 5 | K16: =COUNTIFS('Detalle por mesa'!$B:$B,$B16,'Detalle por mesa'!$G:$G,"Secundario") -> 10 | L16: Alcaldías Locales 1, 2 y 3; Instituto Distrital de Acción Comunal (IDACC); Secretaría de Participación y Desarrollo Social (SPD/UMATA); Asociaciones de Juntas de Acción Comunal (ASOJAC) (+1 más; ver hoja Detalle) | M16: 20 | N16: =M16/$M$42 -> 0.008 | O16: ='Proyección ±500'!F38 -> 25
B17: Isla Fuerte | C17: Por definir | D17: Por definir | E17: Por definir | F17: Comunitaria | G17: Ambiental | H17: =COUNTIFS('Detalle por mesa'!$B:$B,$B17,'Detalle por mesa'!$I:$I,"Principal")+COUNTIFS('Detalle por mesa'!$B:$B,$B17,'Detalle por mesa'!$I:$I,"Secundario") -> 6 | I17: =COUNTIF('Detalle por mesa'!$B:$B,$B17) -> 15 | J17: =COUNTIFS('Detalle por mesa'!$B:$B,$B17,'Detalle por mesa'!$G:$G,"Principal") -> 5 | K17: =COUNTIFS('Detalle por mesa'!$B:$B,$B17,'Detalle por mesa'!$G:$G,"Secundario") -> 10 | L17: Alcaldías Locales 1, 2 y 3; Instituto Distrital de Acción Comunal (IDACC); Secretaría de Participación y Desarrollo Social (SPD/UMATA); Asociaciones de Juntas de Acción Comunal (ASOJAC) (+1 más; ver hoja Detalle) | M17: 25 | N17: =M17/$M$42 -> 0.01 | O17: ='Proyección ±500'!F39 -> 25
A19: Mesas Poblacionales | B19: Adulto mayor | C19: Por definir | D19: Por definir | E19: Por definir | F19: Comunitaria | G19: Personal | H19: =COUNTIFS('Detalle por mesa'!$B:$B,$B19,'Detalle por mesa'!$I:$I,"Principal")+COUNTIFS('Detalle por mesa'!$B:$B,$B19,'Detalle por mesa'!$I:$I,"Secundario") -> 1 | I19: =COUNTIF('Detalle por mesa'!$B:$B,$B19) -> 7 | J19: =COUNTIFS('Detalle por mesa'!$B:$B,$B19,'Detalle por mesa'!$G:$G,"Principal") -> 3 | K19: =COUNTIFS('Detalle por mesa'!$B:$B,$B19,'Detalle por mesa'!$G:$G,"Secundario") -> 4 | L19: Instituto Distrital de Deporte y Recreación (IDER); Secretaría de Participación y Desarrollo Social (SPD/UMATA); Asociación de Adultos Mayores de Cartagena | M19: 65 | N19: =M19/$M$42 -> 0.026 | O19: ='Proyección ±500'!F42 -> 80
B20: Infancia | C20: Por definir | D20: Por definir | E20: Por definir | F20: Personal | G20: Alimentaria; Comunitaria | H20: =COUNTIFS('Detalle por mesa'!$B:$B,$B20,'Detalle por mesa'!$I:$I,"Principal")+COUNTIFS('Detalle por mesa'!$B:$B,$B20,'Detalle por mesa'!$I:$I,"Secundario") -> 1 | I20: =COUNTIF('Detalle por mesa'!$B:$B,$B20) -> 8 | J20: =COUNTIFS('Detalle por mesa'!$B:$B,$B20,'Detalle por mesa'!$G:$G,"Principal") -> 4 | K20: =COUNTIFS('Detalle por mesa'!$B:$B,$B20,'Detalle por mesa'!$G:$G,"Secundario") -> 4 | L20: Secretaría de Educación Distrital (SED); Comisarías de Familia; Fundación Renacer; ICBF - Centro Zonal Cartagena | M20: 75 | N20: =M20/$M$42 -> 0.03 | O20: ='Proyección ±500'!F43 -> 90
B21: LGTBI | C21: Por definir | D21: Por definir | E21: Por definir | F21: Comunitaria | G21: Personal; Política | H21: =COUNTIFS('Detalle por mesa'!$B:$B,$B21,'Detalle por mesa'!$I:$I,"Principal")+COUNTIFS('Detalle por mesa'!$B:$B,$B21,'Detalle por mesa'!$I:$I,"Secundario") -> 3 | I21: =COUNTIF('Detalle por mesa'!$B:$B,$B21) -> 7 | J21: =COUNTIFS('Detalle por mesa'!$B:$B,$B21,'Detalle por mesa'!$G:$G,"Principal") -> 2 | K21: =COUNTIFS('Detalle por mesa'!$B:$B,$B21,'Detalle por mesa'!$G:$G,"Secundario") -> 5 | L21: Secretaría de Participación y Desarrollo Social (SPD/UMATA); Organización derecho a resistir | M21: 40 | N21: =M21/$M$42 -> 0.016 | O21: ='Proyección ±500'!F44 -> 45
B22: Discapacidad | C22: Por definir | D22: Por definir | E22: Por definir | F22: Comunitaria | G22: Política | H22: =COUNTIFS('Detalle por mesa'!$B:$B,$B22,'Detalle por mesa'!$I:$I,"Principal")+COUNTIFS('Detalle por mesa'!$B:$B,$B22,'Detalle por mesa'!$I:$I,"Secundario") -> 1 | I22: =COUNTIF('Detalle por mesa'!$B:$B,$B22) -> 6 | J22: =COUNTIFS('Detalle por mesa'!$B:$B,$B22,'Detalle por mesa'!$G:$G,"Principal") -> 3 | K22: =COUNTIFS('Detalle por mesa'!$B:$B,$B22,'Detalle por mesa'!$G:$G,"Secundario") -> 3 | L22: Instituto Distrital de Deporte y Recreación (IDER); Secretaría de Participación y Desarrollo Social (SPD/UMATA); Asociación de Personas con Discapacidad de Cartagena | M22: 45 | N22: =M22/$M$42 -> 0.018 | O22: ='Proyección ±500'!F45 -> 50
B23: Juventud | C23: Por definir | D23: Por definir | E23: Por definir | F23: Comunitaria | G23: Personal; Económica | H23: =COUNTIFS('Detalle por mesa'!$B:$B,$B23,'Detalle por mesa'!$I:$I,"Principal")+COUNTIFS('Detalle por mesa'!$B:$B,$B23,'Detalle por mesa'!$I:$I,"Secundario") -> 1 | I23: =COUNTIF('Detalle por mesa'!$B:$B,$B23) -> 10 | J23: =COUNTIFS('Detalle por mesa'!$B:$B,$B23,'Detalle por mesa'!$G:$G,"Principal") -> 5 | K23: =COUNTIFS('Detalle por mesa'!$B:$B,$B23,'Detalle por mesa'!$G:$G,"Secundario") -> 5 | L23: Escuela de Gobierno y Liderazgo; Instituto Distrital de Deporte y Recreación (IDER); Corporación Jóvenes por la Paz; Plataforma de Juventudes de Cartagena (+1 más; ver hoja Detalle) | M23: 80 | N23: =M23/$M$42 -> 0.032 | O23: ='Proyección ±500'!F46 -> 95
B24: Mujeres | C24: Por definir | D24: Por definir | E24: Por definir | F24: Personal | G24: Comunitaria | H24: =COUNTIFS('Detalle por mesa'!$B:$B,$B24,'Detalle por mesa'!$I:$I,"Principal")+COUNTIFS('Detalle por mesa'!$B:$B,$B24,'Detalle por mesa'!$I:$I,"Secundario") -> 3 | I24: =COUNTIF('Detalle por mesa'!$B:$B,$B24) -> 11 | J24: =COUNTIFS('Detalle por mesa'!$B:$B,$B24,'Detalle por mesa'!$G:$G,"Principal") -> 6 | K24: =COUNTIFS('Detalle por mesa'!$B:$B,$B24,'Detalle por mesa'!$G:$G,"Secundario") -> 5 | L24: Secretaría de Participación y Desarrollo Social (SPD/UMATA); Casa de la Mujer (violeta); Comisarías de Familia; Corporación Mujeres Tejiendo Paz (+2 más; ver hoja Detalle) | M24: 100 | N24: =M24/$M$42 -> 0.04 | O24: ='Proyección ±500'!F47 -> 125
B25: Victimas | C25: Por definir | D25: Por definir | E25: Por definir | F25: Política | G25: Comunitaria; Personal | H25: =COUNTIFS('Detalle por mesa'!$B:$B,$B25,'Detalle por mesa'!$I:$I,"Principal")+COUNTIFS('Detalle por mesa'!$B:$B,$B25,'Detalle por mesa'!$I:$I,"Secundario") -> 4 | I25: =COUNTIF('Detalle por mesa'!$B:$B,$B25) -> 10 | J25: =COUNTIFS('Detalle por mesa'!$B:$B,$B25,'Detalle por mesa'!$G:$G,"Principal") -> 5 | K25: =COUNTIFS('Detalle por mesa'!$B:$B,$B25,'Detalle por mesa'!$G:$G,"Secundario") -> 5 | L25: Defensoría del Pueblo (Regional Bolívar); Fundación Juan Luis Londoño; Mesa de Víctimas de Cartagena; Personería Distrital (+1 más; ver hoja Detalle) | M25: 60 | N25: =M25/$M$42 -> 0.024 | O25: ='Proyección ±500'!F48 -> 70
B26: Étnica | C26: Por definir | D26: Por definir | E26: Por definir | F26: Comunitaria | G26: — | H26: =COUNTIFS('Detalle por mesa'!$B:$B,$B26,'Detalle por mesa'!$I:$I,"Principal")+COUNTIFS('Detalle por mesa'!$B:$B,$B26,'Detalle por mesa'!$I:$I,"Secundario") -> 2 | I26: =COUNTIF('Detalle por mesa'!$B:$B,$B26) -> 8 | J26: =COUNTIFS('Detalle por mesa'!$B:$B,$B26,'Detalle por mesa'!$G:$G,"Principal") -> 3 | K26: =COUNTIFS('Detalle por mesa'!$B:$B,$B26,'Detalle por mesa'!$G:$G,"Secundario") -> 5 | L26: Consejo Comunitario de la Comunidad Negra de Pasacaballos; Consejo Comunitario de la Comunidad Negra de la Isla de Barú; Red de Jóvenes Afrodescendientes de Cartagena | M26: 80 | N26: =M26/$M$42 -> 0.032 | O26: ='Proyección ±500'!F49 -> 100
B27: Migrantes y refugiados (nueva) | C27: Por definir | D27: Por definir | E27: Por definir | F27: Personal | G27: Política; Comunitaria | H27: =COUNTIFS('Detalle por mesa'!$B:$B,$B27,'Detalle por mesa'!$I:$I,"Principal")+COUNTIFS('Detalle por mesa'!$B:$B,$B27,'Detalle por mesa'!$I:$I,"Secundario") -> 3 | I27: =COUNTIF('Detalle por mesa'!$B:$B,$B27) -> 10 | J27: =COUNTIFS('Detalle por mesa'!$B:$B,$B27,'Detalle por mesa'!$G:$G,"Principal") -> 5 | K27: =COUNTIFS('Detalle por mesa'!$B:$B,$B27,'Detalle por mesa'!$G:$G,"Secundario") -> 5 | L27: ACNUR - Agencia de la ONU para los Refugiados; Asociación de Venezolanos en Cartagena (AVEC); Fundación Colombia Somos Todos; Migración Colombia (Regional Bolívar) (+1 más; ver hoja Detalle) | M27: 55 | N27: =M27/$M$42 -> 0.022 | O27: ='Proyección ±500'!F50 -> 65
A29: Mesas Sectoriales | B29: Cultura | C29: Por definir | D29: Por definir | E29: Por definir | F29: Comunitaria | G29: Económica | H29: =COUNTIFS('Detalle por mesa'!$B:$B,$B29,'Detalle por mesa'!$I:$I,"Principal")+COUNTIFS('Detalle por mesa'!$B:$B,$B29,'Detalle por mesa'!$I:$I,"Secundario") -> 0 | I29: =COUNTIF('Detalle por mesa'!$B:$B,$B29) -> 6 | J29: =COUNTIFS('Detalle por mesa'!$B:$B,$B29,'Detalle por mesa'!$G:$G,"Principal") -> 3 | K29: =COUNTIFS('Detalle por mesa'!$B:$B,$B29,'Detalle por mesa'!$G:$G,"Secundario") -> 3 | L29: Escuela Taller de Cartagena de Indias (ETCAR); Instituto de Patrimonio y Cultura de Cartagena (IPCC); Universidad de Bellas Artes | M29: 30 | N29: =M29/$M$42 -> 0.012 | O29: ='Proyección ±500'!F53 -> 35
B30: Deporte | C30: Por definir | D30: Por definir | E30: Por definir | F30: Comunitaria | G30: Salud y sanitaria | H30: =COUNTIFS('Detalle por mesa'!$B:$B,$B30,'Detalle por mesa'!$I:$I,"Principal")+COUNTIFS('Detalle por mesa'!$B:$B,$B30,'Detalle por mesa'!$I:$I,"Secundario") -> 0 | I30: =COUNTIF('Detalle por mesa'!$B:$B,$B30) -> 6 | J30: =COUNTIFS('Detalle por mesa'!$B:$B,$B30,'Detalle por mesa'!$G:$G,"Principal") -> 1 | K30: =COUNTIFS('Detalle por mesa'!$B:$B,$B30,'Detalle por mesa'!$G:$G,"Secundario") -> 5 | L30: Instituto Distrital de Deporte y Recreación (IDER) | M30: 30 | N30: =M30/$M$42 -> 0.012 | O30: ='Proyección ±500'!F54 -> 35
B31: Salud | C31: Por definir | D31: Por definir | E31: Por definir | F31: Salud y sanitaria | G31: — | H31: =COUNTIFS('Detalle por mesa'!$B:$B,$B31,'Detalle por mesa'!$I:$I,"Principal")+COUNTIFS('Detalle por mesa'!$B:$B,$B31,'Detalle por mesa'!$I:$I,"Secundario") -> 1 | I31: =COUNTIF('Detalle por mesa'!$B:$B,$B31) -> 6 | J31: =COUNTIFS('Detalle por mesa'!$B:$B,$B31,'Detalle por mesa'!$G:$G,"Principal") -> 2 | K31: =COUNTIFS('Detalle por mesa'!$B:$B,$B31,'Detalle por mesa'!$G:$G,"Secundario") -> 4 | L31: Departamento Administrativo Distrital de Salud (DADIS); Universidad del Sinú | M31: 30 | N31: =M31/$M$42 -> 0.012 | O31: ='Proyección ±500'!F55 -> 35
B32: Educacion | C32: Por definir | D32: Por definir | E32: Por definir | F32: Comunitaria | G32: Económica | H32: =COUNTIFS('Detalle por mesa'!$B:$B,$B32,'Detalle por mesa'!$I:$I,"Principal")+COUNTIFS('Detalle por mesa'!$B:$B,$B32,'Detalle por mesa'!$I:$I,"Secundario") -> 0 | I32: =COUNTIF('Detalle por mesa'!$B:$B,$B32) -> 15 | J32: =COUNTIFS('Detalle por mesa'!$B:$B,$B32,'Detalle por mesa'!$G:$G,"Principal") -> 6 | K32: =COUNTIFS('Detalle por mesa'!$B:$B,$B32,'Detalle por mesa'!$G:$G,"Secundario") -> 9 | L32: Escuela Taller de Cartagena de Indias (ETCAR); Institución Universitaria Mayor de Cartagena (Colmayor); Secretaría de Educación Distrital (SED); SENA - Regional Bolívar (+2 más; ver hoja Detalle) | M32: 35 | N32: =M32/$M$42 -> 0.014 | O32: ='Proyección ±500'!F56 -> 40
B33: Movilidad y Espacio Público | C33: Por definir | D33: Por definir | E33: Por definir | F33: Económica | G33: Personal | H33: =COUNTIFS('Detalle por mesa'!$B:$B,$B33,'Detalle por mesa'!$I:$I,"Principal")+COUNTIFS('Detalle por mesa'!$B:$B,$B33,'Detalle por mesa'!$I:$I,"Secundario") -> 2 | I33: =COUNTIF('Detalle por mesa'!$B:$B,$B33) -> 8 | J33: =COUNTIFS('Detalle por mesa'!$B:$B,$B33,'Detalle por mesa'!$G:$G,"Principal") -> 5 | K33: =COUNTIFS('Detalle por mesa'!$B:$B,$B33,'Detalle por mesa'!$G:$G,"Secundario") -> 3 | L33: Departamento Administrativo de Tránsito y Transporte (DATT); Gerencia de Espacio Público y Movilidad (GEPM); Transcaribe S.A.; Asociación de Trabajadores Informales de Cartagena (+1 más; ver hoja Detalle) | M33: 30 | N33: =M33/$M$42 -> 0.012 | O33: ='Proyección ±500'!F57 -> 35
B34: Servicios públicos, infraestructura y vivienda | C34: Por definir | D34: Por definir | E34: Por definir | F34: Ambiental | G34: Económica; Comunitaria | H34: =COUNTIFS('Detalle por mesa'!$B:$B,$B34,'Detalle por mesa'!$I:$I,"Principal")+COUNTIFS('Detalle por mesa'!$B:$B,$B34,'Detalle por mesa'!$I:$I,"Secundario") -> 1 | I34: =COUNTIF('Detalle por mesa'!$B:$B,$B34) -> 11 | J34: =COUNTIFS('Detalle por mesa'!$B:$B,$B34,'Detalle por mesa'!$G:$G,"Principal") -> 5 | K34: =COUNTIFS('Detalle por mesa'!$B:$B,$B34,'Detalle por mesa'!$G:$G,"Secundario") -> 6 | L34: Corvivienda; Secretaría General (Oficina de Servicios Públicos - Oficina Asesora Informática); Secretaría de Infraestructura; Líderes de Islas (Tierra Bomba, Barú, etc) (+1 más; ver hoja Detalle) | M34: 35 | N34: =M34/$M$42 -> 0.014 | O34: ='Proyección ±500'!F58 -> 40
B35: Seguridad y Convivencia Ciudadana | C35: Por definir | D35: Por definir | E35: Por definir | F35: Personal | G35: — | H35: =COUNTIFS('Detalle por mesa'!$B:$B,$B35,'Detalle por mesa'!$I:$I,"Principal")+COUNTIFS('Detalle por mesa'!$B:$B,$B35,'Detalle por mesa'!$I:$I,"Secundario") -> 6 | I35: =COUNTIF('Detalle por mesa'!$B:$B,$B35) -> 38 | J35: =COUNTIFS('Detalle por mesa'!$B:$B,$B35,'Detalle por mesa'!$G:$G,"Principal") -> 24 | K35: =COUNTIFS('Detalle por mesa'!$B:$B,$B35,'Detalle por mesa'!$G:$G,"Secundario") -> 14 | L35: Departamento Administrativo de Tránsito y Transporte (DATT); Distriseguridad; Secretaría de Interior y Convivencia Ciudadana (SICC); Asociación de Comerciantes del Centro Histórico (+20 más; ver hoja Detalle) | M35: 40 | N35: =M35/$M$42 -> 0.016 | O35: ='Proyección ±500'!F59 -> 50
B36: Medio ambiente, Gestión del riesgo y Planeación | C36: Por definir | D36: Por definir | E36: Por definir | F36: Ambiental | G36: Política | H36: =COUNTIFS('Detalle por mesa'!$B:$B,$B36,'Detalle por mesa'!$I:$I,"Principal")+COUNTIFS('Detalle por mesa'!$B:$B,$B36,'Detalle por mesa'!$I:$I,"Secundario") -> 12 | I36: =COUNTIF('Detalle por mesa'!$B:$B,$B36) -> 24 | J36: =COUNTIFS('Detalle por mesa'!$B:$B,$B36,'Detalle por mesa'!$G:$G,"Principal") -> 15 | K36: =COUNTIFS('Detalle por mesa'!$B:$B,$B36,'Detalle por mesa'!$G:$G,"Secundario") -> 9 | L36: CARDIQUE; Corvivienda; Cuerpo Oficial de Bomberos; EPA Cartagena; Oficina Asesora para la Gestión del Riesgo y Desastres - OAGRD (+11 más; ver hoja Detalle) | M36: 40 | N36: =M36/$M$42 -> 0.016 | O36: ='Proyección ±500'!F60 -> 50
B37: Desarrollo económico, Turismo / Competitividad , ciencia y tecnología | C37: Por definir | D37: Por definir | E37: Por definir | F37: Económica | G37: — | H37: =COUNTIFS('Detalle por mesa'!$B:$B,$B37,'Detalle por mesa'!$I:$I,"Principal")+COUNTIFS('Detalle por mesa'!$B:$B,$B37,'Detalle por mesa'!$I:$I,"Secundario") -> 0 | I37: =COUNTIF('Detalle por mesa'!$B:$B,$B37) -> 28 | J37: =COUNTIFS('Detalle por mesa'!$B:$B,$B37,'Detalle por mesa'!$G:$G,"Principal") -> 21 | K37: =COUNTIFS('Detalle por mesa'!$B:$B,$B37,'Detalle por mesa'!$G:$G,"Secundario") -> 7 | L37: Corvivienda; Escuela Taller de Cartagena de Indias (ETCAR); Gerencia de Espacio Público y Movilidad (GEPM); Institución Universitaria Mayor de Cartagena (Colmayor) (+17 más; ver hoja Detalle) | M37: 40 | N37: =M37/$M$42 -> 0.016 | O37: ='Proyección ±500'!F61 -> 50
B38: Transparencia y Cultura Ciudadana | C38: Por definir | D38: Por definir | E38: Por definir | F38: Política | G38: — | H38: =COUNTIFS('Detalle por mesa'!$B:$B,$B38,'Detalle por mesa'!$I:$I,"Principal")+COUNTIFS('Detalle por mesa'!$B:$B,$B38,'Detalle por mesa'!$I:$I,"Secundario") -> 2 | I38: =COUNTIF('Detalle por mesa'!$B:$B,$B38) -> 35 | J38: =COUNTIFS('Detalle por mesa'!$B:$B,$B38,'Detalle por mesa'!$G:$G,"Principal") -> 23 | K38: =COUNTIFS('Detalle por mesa'!$B:$B,$B38,'Detalle por mesa'!$G:$G,"Secundario") -> 12 | L38: Secretaría General (Oficina de Servicios Públicos - Oficina Asesora Informática); Secretaría de Planeación Distrital; ACNUR - Agencia de la ONU para los Refugiados; Caracol Radio - Cartagena (+19 más; ver hoja Detalle) | M38: 45 | N38: =M38/$M$42 -> 0.018 | O38: ='Proyección ±500'!F62 -> 55
B39: Mesa de Construcción de Paz | C39: Por definir | D39: Por definir | E39: Por definir | F39: Política | G39: Personal; Comunitaria | H39: =COUNTIFS('Detalle por mesa'!$B:$B,$B39,'Detalle por mesa'!$I:$I,"Principal")+COUNTIFS('Detalle por mesa'!$B:$B,$B39,'Detalle por mesa'!$I:$I,"Secundario") -> 2 | I39: =COUNTIF('Detalle por mesa'!$B:$B,$B39) -> 17 | J39: =COUNTIFS('Detalle por mesa'!$B:$B,$B39,'Detalle por mesa'!$G:$G,"Principal") -> 11 | K39: =COUNTIFS('Detalle por mesa'!$B:$B,$B39,'Detalle por mesa'!$G:$G,"Secundario") -> 6 | L39: ACNUR - Agencia de la ONU para los Refugiados; Corporación Jóvenes por la Paz; Corporación Mujeres Tejiendo Paz; Defensoría del Pueblo (Regional Bolívar) (+7 más; ver hoja Detalle) | M39: 35 | N39: =M39/$M$42 -> 0.014 | O39: ='Proyección ±500'!F63 -> 45
B40: Seguridad alimentaria (nueva) | C40: Por definir | D40: Por definir | E40: Por definir | F40: Alimentaria | G40: — | H40: =COUNTIFS('Detalle por mesa'!$B:$B,$B40,'Detalle por mesa'!$I:$I,"Principal")+COUNTIFS('Detalle por mesa'!$B:$B,$B40,'Detalle por mesa'!$I:$I,"Secundario") -> 0 | I40: =COUNTIF('Detalle por mesa'!$B:$B,$B40) -> 5 | J40: =COUNTIFS('Detalle por mesa'!$B:$B,$B40,'Detalle por mesa'!$G:$G,"Principal") -> 1 | K40: =COUNTIFS('Detalle por mesa'!$B:$B,$B40,'Detalle por mesa'!$G:$G,"Secundario") -> 4 | L40: Secretaría de Educación Distrital (SED) | M40: 30 | N40: =M40/$M$42 -> 0.012 | O40: ='Proyección ±500'!F64 -> 35
A42: Total de mesas | B42: =COUNTA(B3:B40) -> 35 | H42: =SUM(H3:H40) -> 105 | I42: =SUM(I3:I40) -> 476 | J42: =SUM(J3:J40) -> 233 | K42: =SUM(K3:K40) -> 243 | M42: =SUM(M3:M40) -> 2500 | O42: =SUM(O3:O40) -> 3000
A43: Mesas por clasificación
A44: Mesas Territoriales | B44: =COUNTA(B3:B5) -> 3
A45: Mesas Rurales | B45: =COUNTA(B7:B17) -> 11
A46: Mesas Poblacionales | B46: =COUNTA(B19:B27) -> 9
A47: Mesas Sectoriales | B47: =COUNTA(B29:B40) -> 12
A50: Mesas por dimensión principal
A51: Comunitaria | B51: =COUNTIF($F$3:$F$40,A51) -> 22
A52: Económica | B52: =COUNTIF($F$3:$F$40,A52) -> 2
A53: Personal | B53: =COUNTIF($F$3:$F$40,A53) -> 4
A54: Política | B54: =COUNTIF($F$3:$F$40,A54) -> 3
A55: Alimentaria | B55: =COUNTIF($F$3:$F$40,A55) -> 1
A56: Ambiental | B56: =COUNTIF($F$3:$F$40,A56) -> 2
A57: Salud y sanitaria | B57: =COUNTIF($F$3:$F$40,A57) -> 1
A58: Crisis (eje transversal) | B58: =COUNTIF($H$3:$H$40,">0") -> 30 | C58: mesas con actores del eje Crisis
A59: *** Las Mesas y sus respectivos horarios son susceptibles a cambios
A60: *** Dirección, fecha y hora quedan "Por definir": la matriz no contiene esa información. Las 7 dimensiones son las de la seguridad humana; Crisis se trata como eje transversal. Las mesas en rojo (Migrantes y refugiados; Seguridad alimentaria) son las 2 mesas nuevas respecto a las 33 del formato original.
A61: *** Los totales de actores cuentan con repeticiones: un mismo actor puede participar en varias mesas. Detalle completo en la hoja "Detalle por mesa"; ver supuestos en "Notas".
A62: *** Meta de personas: 2.500 en total (escenario central), con margen de ±500: mínimo 2.000 y máximo 3.000. Método y parámetros en las hojas "Metas de convocatoria" y "Proyección ±500".

Sheet Metas de convocatoria
A1: METAS DE CONVOCATORIA POR MESA
A2: Texto en azul = dato que se puede editar; celdas amarillas = cifra estimada o provisional por verificar. Todo lo demás se recalcula solo.
A3: PARÁMETROS | C3: Valor | D3: Criterio
A4: Meta total de personas | C4: 2500 | D4: Meta definida para el conjunto de las 35 mesas.
A5: Meta Localidad Histórica y del Caribe Norte | C5: 350 | D5: Definida: 350 personas por reunión de localidad.
A6: Meta Localidad De La Virgen y Turística | C6: 400 | D6: Definida: 400 por su peso demográfico (36,2% de la población en el Censo 2018).
A7: Meta Localidad Industrial y de la Bahía | C7: 350 | D7: Definida: 350 personas por reunión de localidad.
A8: Subtotal localidades | C8: =SUM(C5:C7) -> 1100 | D8: Cifra fija; el resto se reparte entre las otras 32 mesas.
A9: Bloque: mesas rurales (11) | C9: 380 | D9: Propuesta: piso de 20 personas por corregimiento más el excedente según población. Equivale a 15% de la meta, por encima del 10,6% de población rural, para que los corregimientos pequeños tengan una reunión viable.
A10: Bloque: mesas poblacionales (9) | C10: 600 | D10: Propuesta: 24% de la meta; son grupos grandes y con alta superposición entre sí (por ejemplo, mujeres y víctimas).
A11: Bloque: mesas sectoriales (12) | C11: =C4-C8-C9-C10 -> 420 | D11: Es el saldo: meta total menos localidades, rurales y poblacionales.
A12: Piso mínimo por mesa rural | C12: 20 | D12: Propuesta: reunión comunitaria mínima viable.
A13: Piso mínimo por mesa poblacional | C13: 30 | D13: Propuesta: evita que los grupos pequeños (LGTBI, discapacidad) queden con metas simbólicas.
A14: Piso mínimo por mesa sectorial | C14: 20 | D14: Propuesta.
A15: Exponente de ponderación: rurales | C15: 1 | D15: 1 = proporcional a la población; 0,5 = atenúa diferencias; 0 = todas iguales.
A16: Exponente de ponderación: poblacionales | C16: 0.5 | D16: 0,5 = raíz cuadrada de la población. Con 1, "mujeres" (524 mil) absorbería casi todo el bloque.
A17: Exponente de ponderación: sectoriales | C17: 0.5 | D17: Los sectoriales convocan organizaciones, no residentes; se ponderan por el número de actores de la matriz.
A18: Población de Cartagena 2025 (proyección DANE) | C18: 1011520 | D18: Planeación Distrital con datos DANE (El Universal, ago. 2025).
A19: Población censada 2018 (DANE) | C19: 887666 | D19: Síntesis del Diagnóstico Territorial del POT, Planeación Distrital 2025.
A20: Población de Cartagena 2024 (proyección DANE) | C20: 1010408 | D20: Síntesis del Diagnóstico Territorial del POT, Planeación Distrital 2025.
A22: MESAS TERRITORIALES
A23: Clasificación | B23: Mesa | C23: Población aprox. (Censo 2018 × peso) | D23: Peso de la localidad (Censo 2018) | F23: Meta si fuera estrictamente proporcional (referencia) | G23: Meta de personas | H23: Meta / población | I23: Fuente y nota
A24: Mesas Territoriales | B24: Localidad Histórica y del Caribe Norte | C24: =ROUND($C$19*D24,0) -> 242067 | D24: 0.2727 | F24: =ROUND($C$8*D24/SUM($D$24:$D$26),0) -> 303 | G24: =$C$5 -> 350 | H24: =G24/C24 -> 0.0014458807 | I24: Meta fijada por el equipo. Pesos de la localidad: Síntesis del Diagnóstico Territorial del POT (Planeación Distrital 2025), Censo 2018.
A25: Mesas Territoriales | B25: Localidad De La Virgen y Turística | C25: =ROUND($C$19*D25,0) -> 321246 | D25: 0.3619 | F25: =ROUND($C$8*D25/SUM($D$24:$D$26),0) -> 403 | G25: =$C$6 -> 400 | H25: =G25/C25 -> 0.0012451517 | I25: Meta fijada por el equipo. Pesos de la localidad: Síntesis del Diagnóstico Territorial del POT (Planeación Distrital 2025), Censo 2018.
A26: Mesas Territoriales | B26: Localidad Industrial y de la Bahía | C26: =ROUND($C$19*D26,0) -> 314411 | D26: 0.3542 | F26: =ROUND($C$8*D26/SUM($D$24:$D$26),0) -> 394 | G26: =$C$7 -> 350 | H26: =G26/C26 -> 0.0011131926 | I26: Meta fijada por el equipo. Pesos de la localidad: Síntesis del Diagnóstico Territorial del POT (Planeación Distrital 2025), Censo 2018.
A27: Subtotal Mesas Territoriales | G27: =SUM(G24:G26) -> 1100
A29: MESAS RURALES
A30: Clasificación | B30: Mesa | C30: Población del corregimiento | D30: Calidad del dato | E30: Peso | F30: Meta calculada | G30: Meta de personas | H30: Meta / población | I30: Fuente y nota
A31: Mesas Rurales | B31: Boquilla | C31: 14106 | D31: Oficial | E31: =POWER(C31,$C$15) -> 14106 | F31: =$C$12+($C$9-11*$C$12)*E31/SUM($E$31:$E$41) -> 58.176559 | G31: =ROUND(F31/5,0)*5 -> 60 | H31: =G31/C31 -> 0.0042535091 | I31: POT, Documento resumen (seguimientopot.cartagena.gov.co); la fuente no indica el año de la cifra.
A32: Mesas Rurales | B32: Arroyo de Piedra | C32: 1599 | D32: Oficial | E32: =POWER(C32,$C$15) -> 1599 | F32: =$C$12+($C$9-11*$C$12)*E32/SUM($E$31:$E$41) -> 24.327543 | G32: =ROUND(F32/5,0)*5 -> 25 | H32: =G32/C32 -> 0.015634772 | I32: POT, Documento resumen (seguimientopot.cartagena.gov.co); la fuente no indica el año de la cifra.
A33: Mesas Rurales | B33: Punta Canoa | C33: 815 | D33: Oficial | E33: =POWER(C33,$C$15) -> 815 | F33: =$C$12+($C$9-11*$C$12)*E33/SUM($E$31:$E$41) -> 22.205721 | G33: =ROUND(F33/5,0)*5 -> 20 | H33: =G33/C33 -> 0.024539877 | I33: POT, Documento resumen (seguimientopot.cartagena.gov.co); la fuente no indica el año de la cifra.
A34: Mesas Rurales | B34: Bayunca | C34: =ROUND(8107/0.518,-2) -> 15700 | D34: Estimación | E34: =POWER(C34,$C$15) -> 15700 | F34: =$C$12+($C$9-11*$C$12)*E34/SUM($E$31:$E$41) -> 62.49057 | G34: =$C$9-(SUM(G31:G33)+SUM(G35:G41)) -> 65 | H34: =G34/C34 -> 0.0041401274 | I34: Estimación: 8.107 mujeres en Bayunca (Censo 2018, Planeación Distrital) ÷ 51,8% de mujeres. Verificar. Esta fila absorbe el redondeo para que el bloque cuadre.
A35: Mesas Rurales | B35: Pasacaballos | C35: 10648 | D35: Oficial | E35: =POWER(C35,$C$15) -> 10648 | F35: =$C$12+($C$9-11*$C$12)*E35/SUM($E$31:$E$41) -> 48.817808 | G35: =ROUND(F35/5,0)*5 -> 50 | H35: =G35/C35 -> 0.0046957175 | I35: POT, Documento resumen (seguimientopot.cartagena.gov.co); la fuente no indica el año de la cifra.
A36: Mesas Rurales | B36: Arroyo Grande | C36: 2380 | D36: Oficial | E36: =POWER(C36,$C$15) -> 2380 | F36: =$C$12+($C$9-11*$C$12)*E36/SUM($E$31:$E$41) -> 26.441246 | G36: =ROUND(F36/5,0)*5 -> 25 | H36: =G36/C36 -> 0.010504202 | I36: POT, Documento resumen (seguimientopot.cartagena.gov.co); la fuente no indica el año de la cifra.
A37: Mesas Rurales | B37: Santa Ana | C37: 2990 | D37: Oficial | E37: =POWER(C37,$C$15) -> 2990 | F37: =$C$12+($C$9-11*$C$12)*E37/SUM($E$31:$E$41) -> 28.092153 | G37: =ROUND(F37/5,0)*5 -> 30 | H37: =G37/C37 -> 0.010033445 | I37: POT, Documento resumen (seguimientopot.cartagena.gov.co); la fuente no indica el año de la cifra.
A38: Mesas Rurales | B38: Tierra bomba | C38: 4300 | D38: Provisional | E38: =POWER(C38,$C$15) -> 4300 | F38: =$C$12+($C$9-11*$C$12)*E38/SUM($E$31:$E$41) -> 31.637545 | G38: =ROUND(F38/5,0)*5 -> 30 | H38: =G38/C38 -> 0.0069767442 | I38: Provisional: no hallé cifra oficial; se asumió similar a Bocachica (misma isla). Reemplazar con el dato de Planeación.
A39: Mesas Rurales | B39: Bocachica | C39: 4269 | D39: Oficial | E39: =POWER(C39,$C$15) -> 4269 | F39: =$C$12+($C$9-11*$C$12)*E39/SUM($E$31:$E$41) -> 31.553646 | G39: =ROUND(F39/5,0)*5 -> 30 | H39: =G39/C39 -> 0.0070274069 | I39: POT, Documento resumen (seguimientopot.cartagena.gov.co); la fuente no indica el año de la cifra.
A40: Mesas Rurales | B40: Isla del Rosario | C40: 735 | D40: Oficial | E40: =POWER(C40,$C$15) -> 735 | F40: =$C$12+($C$9-11*$C$12)*E40/SUM($E$31:$E$41) -> 21.989208 | G40: =ROUND(F40/5,0)*5 -> 20 | H40: =G40/C40 -> 0.027210884 | I40: POT, Documento resumen (seguimientopot.cartagena.gov.co); la fuente no indica el año de la cifra.
A41: Mesas Rurales | B41: Isla Fuerte | C41: 1577 | D41: Oficial | E41: =POWER(C41,$C$15) -> 1577 | F41: =$C$12+($C$9-11*$C$12)*E41/SUM($E$31:$E$41) -> 24.268002 | G41: =ROUND(F41/5,0)*5 -> 25 | H41: =G41/C41 -> 0.015852885 | I41: POT, Documento resumen (seguimientopot.cartagena.gov.co); la fuente no indica el año de la cifra.
A42: Subtotal Mesas Rurales | G42: =SUM(G31:G41) -> 380
A44: MESAS POBLACIONALES
A45: Clasificación | B45: Mesa | C45: Población de referencia | D45: Dato de base | E45: Peso | F45: Meta calculada | G45: Meta de personas | H45: Meta / población | I45: Fuente y nota
A46: Mesas Poblacionales | B46: Adulto mayor | C46: =ROUND($C$18*0.14,-2) -> 141600 | D46: Adultos mayores: 14,0% de la población 2025 | E46: =POWER(C46,$C$16) -> 376.29775 | F46: =$C$13+($C$10-9*$C$13)*E46/SUM($E$46:$E$54) -> 66.610992 | G46: =ROUND(F46/5,0)*5 -> 65 | H46: =G46/C46 -> 0.00045903955 | I46: DANE, proyección 2025 (telencuestas.com).
A47: Mesas Poblacionales | B47: Infancia | C47: =ROUND($C$18*0.19,-2) -> 192200 | D47: Menores de 12 años: 19,0% de la población 2025 | E47: =POWER(C47,$C$16) -> 438.4062 | F47: =$C$13+($C$10-9*$C$13)*E47/SUM($E$46:$E$54) -> 72.653685 | G47: =ROUND(F47/5,0)*5 -> 75 | H47: =G47/C47 -> 0.00039021852 | I47: DANE, proyección 2025 (telencuestas.com).
A48: Mesas Poblacionales | B48: LGTBI | C48: =ROUND($C$18*0.01,-2) -> 10100 | D48: 1% de los habitantes se identifica como LGBTIQ+ (ENCV 2023) | E48: =POWER(C48,$C$16) -> 100.49876 | F48: =$C$13+($C$10-9*$C$13)*E48/SUM($E$46:$E$54) -> 39.777787 | G48: =ROUND(F48/5,0)*5 -> 40 | H48: =G48/C48 -> 0.003960396 | I48: DANE ENCV 2023, citada en la Síntesis del Diagnóstico del POT 2025. Dato de autorreconocimiento: probable subestimación.
A49: Mesas Poblacionales | B49: Discapacidad | C49: 21951 | D49: Personas con discapacidad, Censo 2018 (2,2%) | E49: =POWER(C49,$C$16) -> 148.1587 | F49: =$C$13+($C$10-9*$C$13)*E49/SUM($E$46:$E$54) -> 44.414747 | G49: =ROUND(F49/5,0)*5 -> 45 | H49: =G49/C49 -> 0.0020500205 | I49: DANE Censo 2018, citado en la Síntesis del POT 2025. El RLCPD certificó 23.570 entre 2002 y 2020.
A50: Mesas Poblacionales | B50: Juventud | C50: =ROUND($C$20*0.247,-2) -> 249600 | D50: 24,7 jóvenes por cada 100 habitantes (2024) | E50: =POWER(C50,$C$16) -> 499.59984 | F50: =$C$13+($C$10-9*$C$13)*E50/SUM($E$46:$E$54) -> 78.607374 | G50: =ROUND(F50/5,0)*5 -> 80 | H50: =G50/C50 -> 0.00032051282 | I50: Síntesis del Diagnóstico del POT 2025 (índice de juventud).
A51: Mesas Poblacionales | B51: Mujeres | C51: 524101 | D51: Mujeres 2025 (51,8% de la población) | E51: =POWER(C51,$C$16) -> 723.9482 | F51: =$C$13+($C$10-9*$C$13)*E51/SUM($E$46:$E$54) -> 100.43481 | G51: =$C$10-(SUM(G46:G50)+SUM(G52:G54)) -> 100 | H51: =G51/C51 -> 0.00019080292 | I51: DANE, proyección 2025 (telencuestas.com). Esta fila absorbe el redondeo para que el bloque cuadre.
A52: Mesas Poblacionales | B52: Victimas | C52: 91804 | D52: Víctimas con última ubicación conocida en Cartagena, fines de 2024 | E52: =POWER(C52,$C$16) -> 302.99175 | F52: =$C$13+($C$10-9*$C$13)*E52/SUM($E$46:$E$54) -> 59.478859 | G52: =ROUND(F52/5,0)*5 -> 60 | H52: =G52/C52 -> 0.00065356629 | I52: Unidad para las Víctimas, citada en la Síntesis del POT 2025.
A53: Mesas Poblacionales | B53: Étnica | C53: =ROUND($C$18*0.286,-2)+1300 -> 290600 | D53: NARP 28,6% (ENCV 2023) más 1.300 indígenas (Censo 2018) | E53: =POWER(C53,$C$16) -> 539.07328 | F53: =$C$13+($C$10-9*$C$13)*E53/SUM($E$46:$E$54) -> 82.447848 | G53: =ROUND(F53/5,0)*5 -> 80 | H53: =G53/C53 -> 0.0002752925 | I53: DANE, citado en la Síntesis del POT 2025. El Censo 2018 contó solo 179.901 personas NARP (subregistro).
A54: Mesas Poblacionales | B54: Migrantes y refugiados (nueva) | C54: 69093 | D54: Población venezolana residente, 2024 (6,5%) | E54: =POWER(C54,$C$16) -> 262.85547 | F54: =$C$13+($C$10-9*$C$13)*E54/SUM($E$46:$E$54) -> 55.573896 | G54: =ROUND(F54/5,0)*5 -> 55 | H54: =G54/C54 -> 0.00079602854 | I54: Migración Colombia 2024, citada en la Síntesis del POT 2025.
A55: Subtotal Mesas Poblacionales | G55: =SUM(G46:G54) -> 600
A57: MESAS SECTORIALES
A58: Clasificación | B58: Mesa | C58: Actores de la matriz | D58: Dato de base | E58: Peso | F58: Meta calculada | G58: Meta de personas | H58: Meta / población | I58: Fuente y nota
A59: Mesas Sectoriales | B59: Cultura | C59: =COUNTIF('Detalle por mesa'!$B:$B,B59) -> 6 | D59: Actores principales y secundarios en la hoja Detalle | E59: =POWER(C59,$C$17) -> 2.4494897 | F59: =$C$14+($C$11-12*$C$14)*E59/SUM($E$59:$E$70) -> 29.585657 | G59: =ROUND(F59/5,0)*5 -> 30 | I59: Los sectoriales convocan organizaciones; el peso es el número de actores identificados en la matriz.
A60: Mesas Sectoriales | B60: Deporte | C60: =COUNTIF('Detalle por mesa'!$B:$B,B60) -> 6 | D60: Actores principales y secundarios en la hoja Detalle | E60: =POWER(C60,$C$17) -> 2.4494897 | F60: =$C$14+($C$11-12*$C$14)*E60/SUM($E$59:$E$70) -> 29.585657 | G60: =ROUND(F60/5,0)*5 -> 30 | I60: Los sectoriales convocan organizaciones; el peso es el número de actores identificados en la matriz.
A61: Mesas Sectoriales | B61: Salud | C61: =COUNTIF('Detalle por mesa'!$B:$B,B61) -> 6 | D61: Actores principales y secundarios en la hoja Detalle | E61: =POWER(C61,$C$17) -> 2.4494897 | F61: =$C$14+($C$11-12*$C$14)*E61/SUM($E$59:$E$70) -> 29.585657 | G61: =ROUND(F61/5,0)*5 -> 30 | I61: Los sectoriales convocan organizaciones; el peso es el número de actores identificados en la matriz.
A62: Mesas Sectoriales | B62: Educacion | C62: =COUNTIF('Detalle por mesa'!$B:$B,B62) -> 15 | D62: Actores principales y secundarios en la hoja Detalle | E62: =POWER(C62,$C$17) -> 3.8729833 | F62: =$C$14+($C$11-12*$C$14)*E62/SUM($E$59:$E$70) -> 35.156255 | G62: =ROUND(F62/5,0)*5 -> 35 | I62: Los sectoriales convocan organizaciones; el peso es el número de actores identificados en la matriz.
A63: Mesas Sectoriales | B63: Movilidad y Espacio Público | C63: =COUNTIF('Detalle por mesa'!$B:$B,B63) -> 8 | D63: Actores principales y secundarios en la hoja Detalle | E63: =POWER(C63,$C$17) -> 2.8284271 | F63: =$C$14+($C$11-12*$C$14)*E63/SUM($E$59:$E$70) -> 31.068563 | G63: =ROUND(F63/5,0)*5 -> 30 | I63: Los sectoriales convocan organizaciones; el peso es el número de actores identificados en la matriz.
A64: Mesas Sectoriales | B64: Servicios públicos, infraestructura y vivienda | C64: =COUNTIF('Detalle por mesa'!$B:$B,B64) -> 11 | D64: Actores principales y secundarios en la hoja Detalle | E64: =POWER(C64,$C$17) -> 3.3166248 | F64: =$C$14+($C$11-12*$C$14)*E64/SUM($E$59:$E$70) -> 32.979041 | G64: =ROUND(F64/5,0)*5 -> 35 | I64: Los sectoriales convocan organizaciones; el peso es el número de actores identificados en la matriz.
A65: Mesas Sectoriales | B65: Seguridad y Convivencia Ciudadana | C65: =COUNTIF('Detalle por mesa'!$B:$B,B65) -> 38 | D65: Actores principales y secundarios en la hoja Detalle | E65: =POWER(C65,$C$17) -> 6.164414 | F65: =$C$14+($C$11-12*$C$14)*E65/SUM($E$59:$E$70) -> 44.123375 | G65: =$C$11-(SUM(G59:G64)+SUM(G66:G70)) -> 40 | I65: Los sectoriales convocan organizaciones; el peso es el número de actores identificados en la matriz. Esta fila absorbe el redondeo para que el bloque cuadre.
A66: Mesas Sectoriales | B66: Medio ambiente, Gestión del riesgo y Planeación | C66: =COUNTIF('Detalle por mesa'!$B:$B,B66) -> 24 | D66: Actores principales y secundarios en la hoja Detalle | E66: =POWER(C66,$C$17) -> 4.8989795 | F66: =$C$14+($C$11-12*$C$14)*E66/SUM($E$59:$E$70) -> 39.171314 | G66: =ROUND(F66/5,0)*5 -> 40 | I66: Los sectoriales convocan organizaciones; el peso es el número de actores identificados en la matriz.
A67: Mesas Sectoriales | B67: Desarrollo económico, Turismo / Competitividad , ciencia y tecnología | C67: =COUNTIF('Detalle por mesa'!$B:$B,B67) -> 28 | D67: Actores principales y secundarios en la hoja Detalle | E67: =POWER(C67,$C$17) -> 5.2915026 | F67: =$C$14+($C$11-12*$C$14)*E67/SUM($E$59:$E$70) -> 40.707386 | G67: =ROUND(F67/5,0)*5 -> 40 | I67: Los sectoriales convocan organizaciones; el peso es el número de actores identificados en la matriz.
A68: Mesas Sectoriales | B68: Transparencia y Cultura Ciudadana | C68: =COUNTIF('Detalle por mesa'!$B:$B,B68) -> 35 | D68: Actores principales y secundarios en la hoja Detalle | E68: =POWER(C68,$C$17) -> 5.9160798 | F68: =$C$14+($C$11-12*$C$14)*E68/SUM($E$59:$E$70) -> 43.151561 | G68: =ROUND(F68/5,0)*5 -> 45 | I68: Los sectoriales convocan organizaciones; el peso es el número de actores identificados en la matriz.
A69: Mesas Sectoriales | B69: Mesa de Construcción de Paz | C69: =COUNTIF('Detalle por mesa'!$B:$B,B69) -> 17 | D69: Actores principales y secundarios en la hoja Detalle | E69: =POWER(C69,$C$17) -> 4.1231056 | F69: =$C$14+($C$11-12*$C$14)*E69/SUM($E$59:$E$70) -> 36.135065 | G69: =ROUND(F69/5,0)*5 -> 35 | I69: Los sectoriales convocan organizaciones; el peso es el número de actores identificados en la matriz.
A70: Mesas Sectoriales | B70: Seguridad alimentaria (nueva) | C70: =COUNTIF('Detalle por mesa'!$B:$B,B70) -> 5 | D70: Actores principales y secundarios en la hoja Detalle | E70: =POWER(C70,$C$17) -> 2.236068 | F70: =$C$14+($C$11-12*$C$14)*E70/SUM($E$59:$E$70) -> 28.750468 | G70: =ROUND(F70/5,0)*5 -> 30 | I70: Los sectoriales convocan organizaciones; el peso es el número de actores identificados en la matriz.
A71: Subtotal Mesas Sectoriales | G71: =SUM(G59:G70) -> 420
A73: TOTAL DE PERSONAS (35 mesas) | G73: =G27+G42+G55+G71 -> 2500
A74: Diferencia frente a la meta (debe ser 0) | G74: =G73-C4 -> 0

Sheet Proyección ±500
A1: PROYECCIÓN DE CONVOCATORIA CON MARGEN DE ERROR (±500 PERSONAS)
A2: Tres escenarios para las 35 mesas: mínimo (meta − margen), central (meta) y máximo (meta + margen). Se aplica el mismo método de la hoja "Metas de convocatoria" (piso por mesa + reparto por peso). Texto azul = dato editable; verde = vínculo a otra hoja; el resto se recalcula solo.
A4: PARÁMETROS | C4: Valor | D4: Criterio
A5: Meta central de personas | C5: ='Metas de convocatoria'!C4 -> 2500 | D5: Vínculo a la meta total de la hoja "Metas de convocatoria" (2.500, definida por el equipo).
A6: Margen de error (personas) | C6: 500 | D6: Definido por el equipo: ±500 personas sobre la meta central.
A7: Escenario mínimo | C7: =C5-C6 -> 2000 | D7: Meta central menos el margen.
A8: Escenario máximo | C8: =C5+C6 -> 3000 | D8: Meta central más el margen.
A9: Margen relativo | C9: =C6/C5 -> 0.2 | D9: Proporción del margen sobre la meta central; se aplica por igual a localidades, rurales y poblacionales.
A10: Factor escenario mínimo | C10: =C7/C5 -> 0.8 | D10: Multiplica las metas de bloque del escenario central.
A11: Factor escenario máximo | C11: =C8/C5 -> 1.2 | D11: Multiplica las metas de bloque del escenario central.
A13: RESUMEN POR BLOQUE
A14: Bloque | B14: N° de mesas | C14: Mínimo | D14: Central | E14: Máximo | F14: Diferencia mín.–máx. | G14: % del total (central) | H14: Regla de cálculo
A15: Mesas Territoriales | B15: 3 | C15: =D27 -> 880 | D15: ='Metas de convocatoria'!C8 -> 1100 | E15: =F27 -> 1320 | F15: =E15-C15 -> 440 | G15: =D15/D$19 -> 0.44 | H15: Cada localidad: meta central × factor, redondeada a múltiplo de 5.
A16: Mesas Rurales | B16: 11 | C16: =ROUND(D16*$C$10/5,0)*5 -> 305 | D16: ='Metas de convocatoria'!C9 -> 380 | E16: =ROUND(D16*$C$11/5,0)*5 -> 455 | F16: =E16-C16 -> 150 | G16: =D16/D$19 -> 0.152 | H16: Bloque central × factor (múltiplo de 5); dentro del bloque, piso de 20 + reparto por población.
A17: Mesas Poblacionales | B17: 9 | C17: =ROUND(D17*$C$10/5,0)*5 -> 480 | D17: ='Metas de convocatoria'!C10 -> 600 | E17: =ROUND(D17*$C$11/5,0)*5 -> 720 | F17: =E17-C17 -> 240 | G17: =D17/D$19 -> 0.24 | H17: Bloque central × factor (múltiplo de 5); piso de 30 + reparto por raíz de la población.
A18: Mesas Sectoriales | B18: 12 | C18: =$C$7-SUM(C15:C17) -> 335 | D18: ='Metas de convocatoria'!C11 -> 420 | E18: =$C$8-SUM(E15:E17) -> 505 | F18: =E18-C18 -> 170 | G18: =D18/D$19 -> 0.168 | H18: Saldo: escenario total menos los otros tres bloques; piso de 20 + reparto por raíz del n° de actores.
A19: Total | B19: =SUM(B15:B18) -> 35 | C19: =SUM(C15:C18) -> 2000 | D19: =SUM(D15:D18) -> 2500 | E19: =SUM(E15:E18) -> 3000 | F19: =SUM(F15:F18) -> 1000 | G19: =SUM(G15:G18) -> 1 | H19: Debe coincidir con 2.000 / 2.500 / 3.000.
A22: PROYECCIÓN POR MESA
A23: Clasificación | B23: Mesa | C23: Peso (hoja Metas) | D23: Mínimo | E23: Central | F23: Máximo | G23: Diferencia mín.–máx. | H23: Nota
A24: Mesas Territoriales | B24: ='Metas de convocatoria'!B24 -> Localidad Histórica y del Caribe Norte | C24: — | D24: =ROUND('Metas de convocatoria'!C5*$C$10/5,0)*5 -> 280 | E24: ='Metas de convocatoria'!G24 -> 350 | F24: =ROUND('Metas de convocatoria'!C5*$C$11/5,0)*5 -> 420 | G24: =F24-D24 -> 140 | H24: Meta fija de la localidad × factor del escenario.
A25: Mesas Territoriales | B25: ='Metas de convocatoria'!B25 -> Localidad De La Virgen y Turística | C25: — | D25: =ROUND('Metas de convocatoria'!C6*$C$10/5,0)*5 -> 320 | E25: ='Metas de convocatoria'!G25 -> 400 | F25: =ROUND('Metas de convocatoria'!C6*$C$11/5,0)*5 -> 480 | G25: =F25-D25 -> 160 | H25: Meta fija de la localidad × factor del escenario.
A26: Mesas Territoriales | B26: ='Metas de convocatoria'!B26 -> Localidad Industrial y de la Bahía | C26: — | D26: =ROUND('Metas de convocatoria'!C7*$C$10/5,0)*5 -> 280 | E26: ='Metas de convocatoria'!G26 -> 350 | F26: =ROUND('Metas de convocatoria'!C7*$C$11/5,0)*5 -> 420 | G26: =F26-D26 -> 140 | H26: Meta fija de la localidad × factor del escenario.
A27: Subtotal Territoriales | D27: =SUM(D24:D26) -> 880 | E27: =SUM(E24:E26) -> 1100 | F27: =SUM(F24:F26) -> 1320 | G27: =SUM(G24:G26) -> 440
A29: Mesas Rurales | B29: ='Metas de convocatoria'!B31 -> Boquilla | C29: ='Metas de convocatoria'!E31 -> 14106 | D29: =ROUND(('Metas de convocatoria'!$C$12+(C$16-11*'Metas de convocatoria'!$C$12)*$C29/SUM($C$29:$C$39))/5,0)*5 -> 40 | E29: ='Metas de convocatoria'!G31 -> 60 | F29: =ROUND(('Metas de convocatoria'!$C$12+(E$16-11*'Metas de convocatoria'!$C$12)*$C29/SUM($C$29:$C$39))/5,0)*5 -> 75 | G29: =F29-D29 -> 35 | H29: Piso + reparto proporcional al peso.
A30: Mesas Rurales | B30: ='Metas de convocatoria'!B32 -> Arroyo de Piedra | C30: ='Metas de convocatoria'!E32 -> 1599 | D30: =ROUND(('Metas de convocatoria'!$C$12+(C$16-11*'Metas de convocatoria'!$C$12)*$C30/SUM($C$29:$C$39))/5,0)*5 -> 20 | E30: ='Metas de convocatoria'!G32 -> 25 | F30: =ROUND(('Metas de convocatoria'!$C$12+(E$16-11*'Metas de convocatoria'!$C$12)*$C30/SUM($C$29:$C$39))/5,0)*5 -> 25 | G30: =F30-D30 -> 5 | H30: Piso + reparto proporcional al peso.
A31: Mesas Rurales | B31: ='Metas de convocatoria'!B33 -> Punta Canoa | C31: ='Metas de convocatoria'!E33 -> 815 | D31: =ROUND(('Metas de convocatoria'!$C$12+(C$16-11*'Metas de convocatoria'!$C$12)*$C31/SUM($C$29:$C$39))/5,0)*5 -> 20 | E31: ='Metas de convocatoria'!G33 -> 20 | F31: =ROUND(('Metas de convocatoria'!$C$12+(E$16-11*'Metas de convocatoria'!$C$12)*$C31/SUM($C$29:$C$39))/5,0)*5 -> 25 | G31: =F31-D31 -> 5 | H31: Piso + reparto proporcional al peso.
A32: Mesas Rurales | B32: ='Metas de convocatoria'!B34 -> Bayunca | C32: ='Metas de convocatoria'!E34 -> 15700 | D32: =C$16-(SUM(D29:D31)+SUM(D33:D39)) -> 50 | E32: ='Metas de convocatoria'!G34 -> 65 | F32: =E$16-(SUM(F29:F31)+SUM(F33:F39)) -> 90 | G32: =F32-D32 -> 40 | H32: Fila de ajuste: absorbe el redondeo para que el bloque cuadre.
A33: Mesas Rurales | B33: ='Metas de convocatoria'!B35 -> Pasacaballos | C33: ='Metas de convocatoria'!E35 -> 10648 | D33: =ROUND(('Metas de convocatoria'!$C$12+(C$16-11*'Metas de convocatoria'!$C$12)*$C33/SUM($C$29:$C$39))/5,0)*5 -> 35 | E33: ='Metas de convocatoria'!G35 -> 50 | F33: =ROUND(('Metas de convocatoria'!$C$12+(E$16-11*'Metas de convocatoria'!$C$12)*$C33/SUM($C$29:$C$39))/5,0)*5 -> 60 | G33: =F33-D33 -> 25 | H33: Piso + reparto proporcional al peso.
A34: Mesas Rurales | B34: ='Metas de convocatoria'!B36 -> Arroyo Grande | C34: ='Metas de convocatoria'!E36 -> 2380 | D34: =ROUND(('Metas de convocatoria'!$C$12+(C$16-11*'Metas de convocatoria'!$C$12)*$C34/SUM($C$29:$C$39))/5,0)*5 -> 25 | E34: ='Metas de convocatoria'!G36 -> 25 | F34: =ROUND(('Metas de convocatoria'!$C$12+(E$16-11*'Metas de convocatoria'!$C$12)*$C34/SUM($C$29:$C$39))/5,0)*5 -> 30 | G34: =F34-D34 -> 5 | H34: Piso + reparto proporcional al peso.
A35: Mesas Rurales | B35: ='Metas de convocatoria'!B37 -> Santa Ana | C35: ='Metas de convocatoria'!E37 -> 2990 | D35: =ROUND(('Metas de convocatoria'!$C$12+(C$16-11*'Metas de convocatoria'!$C$12)*$C35/SUM($C$29:$C$39))/5,0)*5 -> 25 | E35: ='Metas de convocatoria'!G37 -> 30 | F35: =ROUND(('Metas de convocatoria'!$C$12+(E$16-11*'Metas de convocatoria'!$C$12)*$C35/SUM($C$29:$C$39))/5,0)*5 -> 30 | G35: =F35-D35 -> 5 | H35: Piso + reparto proporcional al peso.
A36: Mesas Rurales | B36: ='Metas de convocatoria'!B38 -> Tierra bomba | C36: ='Metas de convocatoria'!E38 -> 4300 | D36: =ROUND(('Metas de convocatoria'!$C$12+(C$16-11*'Metas de convocatoria'!$C$12)*$C36/SUM($C$29:$C$39))/5,0)*5 -> 25 | E36: ='Metas de convocatoria'!G38 -> 30 | F36: =ROUND(('Metas de convocatoria'!$C$12+(E$16-11*'Metas de convocatoria'!$C$12)*$C36/SUM($C$29:$C$39))/5,0)*5 -> 35 | G36: =F36-D36 -> 10 | H36: Piso + reparto proporcional al peso.
A37: Mesas Rurales | B37: ='Metas de convocatoria'!B39 -> Bocachica | C37: ='Metas de convocatoria'!E39 -> 4269 | D37: =ROUND(('Metas de convocatoria'!$C$12+(C$16-11*'Metas de convocatoria'!$C$12)*$C37/SUM($C$29:$C$39))/5,0)*5 -> 25 | E37: ='Metas de convocatoria'!G39 -> 30 | F37: =ROUND(('Metas de convocatoria'!$C$12+(E$16-11*'Metas de convocatoria'!$C$12)*$C37/SUM($C$29:$C$39))/5,0)*5 -> 35 | G37: =F37-D37 -> 10 | H37: Piso + reparto proporcional al peso.
A38: Mesas Rurales | B38: ='Metas de convocatoria'!B40 -> Isla del Rosario | C38: ='Metas de convocatoria'!E40 -> 735 | D38: =ROUND(('Metas de convocatoria'!$C$12+(C$16-11*'Metas de convocatoria'!$C$12)*$C38/SUM($C$29:$C$39))/5,0)*5 -> 20 | E38: ='Metas de convocatoria'!G40 -> 20 | F38: =ROUND(('Metas de convocatoria'!$C$12+(E$16-11*'Metas de convocatoria'!$C$12)*$C38/SUM($C$29:$C$39))/5,0)*5 -> 25 | G38: =F38-D38 -> 5 | H38: Piso + reparto proporcional al peso.
A39: Mesas Rurales | B39: ='Metas de convocatoria'!B41 -> Isla Fuerte | C39: ='Metas de convocatoria'!E41 -> 1577 | D39: =ROUND(('Metas de convocatoria'!$C$12+(C$16-11*'Metas de convocatoria'!$C$12)*$C39/SUM($C$29:$C$39))/5,0)*5 -> 20 | E39: ='Metas de convocatoria'!G41 -> 25 | F39: =ROUND(('Metas de convocatoria'!$C$12+(E$16-11*'Metas de convocatoria'!$C$12)*$C39/SUM($C$29:$C$39))/5,0)*5 -> 25 | G39: =F39-D39 -> 5 | H39: Piso + reparto proporcional al peso.
A40: Subtotal Rurales | D40: =SUM(D29:D39) -> 305 | E40: =SUM(E29:E39) -> 380 | F40: =SUM(F29:F39) -> 455 | G40: =SUM(G29:G39) -> 150
A42: Mesas Poblacionales | B42: ='Metas de convocatoria'!B46 -> Adulto mayor | C42: ='Metas de convocatoria'!E46 -> 376.29775 | D42: =ROUND(('Metas de convocatoria'!$C$13+(C$17-9*'Metas de convocatoria'!$C$13)*$C42/SUM($C$42:$C$50))/5,0)*5 -> 55 | E42: ='Metas de convocatoria'!G46 -> 65 | F42: =ROUND(('Metas de convocatoria'!$C$13+(E$17-9*'Metas de convocatoria'!$C$13)*$C42/SUM($C$42:$C$50))/5,0)*5 -> 80 | G42: =F42-D42 -> 25 | H42: Piso + reparto proporcional al peso.
A43: Mesas Poblacionales | B43: ='Metas de convocatoria'!B47 -> Infancia | C43: ='Metas de convocatoria'!E47 -> 438.4062 | D43: =ROUND(('Metas de convocatoria'!$C$13+(C$17-9*'Metas de convocatoria'!$C$13)*$C43/SUM($C$42:$C$50))/5,0)*5 -> 55 | E43: ='Metas de convocatoria'!G47 -> 75 | F43: =ROUND(('Metas de convocatoria'!$C$13+(E$17-9*'Metas de convocatoria'!$C$13)*$C43/SUM($C$42:$C$50))/5,0)*5 -> 90 | G43: =F43-D43 -> 35 | H43: Piso + reparto proporcional al peso.
A44: Mesas Poblacionales | B44: ='Metas de convocatoria'!B48 -> LGTBI | C44: ='Metas de convocatoria'!E48 -> 100.49876 | D44: =ROUND(('Metas de convocatoria'!$C$13+(C$17-9*'Metas de convocatoria'!$C$13)*$C44/SUM($C$42:$C$50))/5,0)*5 -> 35 | E44: ='Metas de convocatoria'!G48 -> 40 | F44: =ROUND(('Metas de convocatoria'!$C$13+(E$17-9*'Metas de convocatoria'!$C$13)*$C44/SUM($C$42:$C$50))/5,0)*5 -> 45 | G44: =F44-D44 -> 10 | H44: Piso + reparto proporcional al peso.
A45: Mesas Poblacionales | B45: ='Metas de convocatoria'!B49 -> Discapacidad | C45: ='Metas de convocatoria'!E49 -> 148.1587 | D45: =ROUND(('Metas de convocatoria'!$C$13+(C$17-9*'Metas de convocatoria'!$C$13)*$C45/SUM($C$42:$C$50))/5,0)*5 -> 40 | E45: ='Metas de convocatoria'!G49 -> 45 | F45: =ROUND(('Metas de convocatoria'!$C$13+(E$17-9*'Metas de convocatoria'!$C$13)*$C45/SUM($C$42:$C$50))/5,0)*5 -> 50 | G45: =F45-D45 -> 10 | H45: Piso + reparto proporcional al peso.
A46: Mesas Poblacionales | B46: ='Metas de convocatoria'!B50 -> Juventud | C46: ='Metas de convocatoria'!E50 -> 499.59984 | D46: =ROUND(('Metas de convocatoria'!$C$13+(C$17-9*'Metas de convocatoria'!$C$13)*$C46/SUM($C$42:$C$50))/5,0)*5 -> 60 | E46: ='Metas de convocatoria'!G50 -> 80 | F46: =ROUND(('Metas de convocatoria'!$C$13+(E$17-9*'Metas de convocatoria'!$C$13)*$C46/SUM($C$42:$C$50))/5,0)*5 -> 95 | G46: =F46-D46 -> 35 | H46: Piso + reparto proporcional al peso.
A47: Mesas Poblacionales | B47: ='Metas de convocatoria'!B51 -> Mujeres | C47: ='Metas de convocatoria'!E51 -> 723.9482 | D47: =C$17-(SUM(D42:D46)+SUM(D48:D50)) -> 75 | E47: ='Metas de convocatoria'!G51 -> 100 | F47: =E$17-(SUM(F42:F46)+SUM(F48:F50)) -> 125 | G47: =F47-D47 -> 50 | H47: Fila de ajuste: absorbe el redondeo para que el bloque cuadre.
A48: Mesas Poblacionales | B48: ='Metas de convocatoria'!B52 -> Victimas | C48: ='Metas de convocatoria'!E52 -> 302.99175 | D48: =ROUND(('Metas de convocatoria'!$C$13+(C$17-9*'Metas de convocatoria'!$C$13)*$C48/SUM($C$42:$C$50))/5,0)*5 -> 50 | E48: ='Metas de convocatoria'!G52 -> 60 | F48: =ROUND(('Metas de convocatoria'!$C$13+(E$17-9*'Metas de convocatoria'!$C$13)*$C48/SUM($C$42:$C$50))/5,0)*5 -> 70 | G48: =F48-D48 -> 20 | H48: Piso + reparto proporcional al peso.
A49: Mesas Poblacionales | B49: ='Metas de convocatoria'!B53 -> Étnica | C49: ='Metas de convocatoria'!E53 -> 539.07328 | D49: =ROUND(('Metas de convocatoria'!$C$13+(C$17-9*'Metas de convocatoria'!$C$13)*$C49/SUM($C$42:$C$50))/5,0)*5 -> 65 | E49: ='Metas de convocatoria'!G53 -> 80 | F49: =ROUND(('Metas de convocatoria'!$C$13+(E$17-9*'Metas de convocatoria'!$C$13)*$C49/SUM($C$42:$C$50))/5,0)*5 -> 100 | G49: =F49-D49 -> 35 | H49: Piso + reparto proporcional al peso.
A50: Mesas Poblacionales | B50: ='Metas de convocatoria'!B54 -> Migrantes y refugiados (nueva) | C50: ='Metas de convocatoria'!E54 -> 262.85547 | D50: =ROUND(('Metas de convocatoria'!$C$13+(C$17-9*'Metas de convocatoria'!$C$13)*$C50/SUM($C$42:$C$50))/5,0)*5 -> 45 | E50: ='Metas de convocatoria'!G54 -> 55 | F50: =ROUND(('Metas de convocatoria'!$C$13+(E$17-9*'Metas de convocatoria'!$C$13)*$C50/SUM($C$42:$C$50))/5,0)*5 -> 65 | G50: =F50-D50 -> 20 | H50: Piso + reparto proporcional al peso.
A51: Subtotal Poblacionales | D51: =SUM(D42:D50) -> 480 | E51: =SUM(E42:E50) -> 600 | F51: =SUM(F42:F50) -> 720 | G51: =SUM(G42:G50) -> 240
A53: Mesas Sectoriales | B53: ='Metas de convocatoria'!B59 -> Cultura | C53: ='Metas de convocatoria'!E59 -> 2.4494897 | D53: =ROUND(('Metas de convocatoria'!$C$14+(C$18-12*'Metas de convocatoria'!$C$14)*$C53/SUM($C$53:$C$64))/5,0)*5 -> 25 | E53: ='Metas de convocatoria'!G59 -> 30 | F53: =ROUND(('Metas de convocatoria'!$C$14+(E$18-12*'Metas de convocatoria'!$C$14)*$C53/SUM($C$53:$C$64))/5,0)*5 -> 35 | G53: =F53-D53 -> 10 | H53: Piso + reparto proporcional al peso.
A54: Mesas Sectoriales | B54: ='Metas de convocatoria'!B60 -> Deporte | C54: ='Metas de convocatoria'!E60 -> 2.4494897 | D54: =ROUND(('Metas de convocatoria'!$C$14+(C$18-12*'Metas de convocatoria'!$C$14)*$C54/SUM($C$53:$C$64))/5,0)*5 -> 25 | E54: ='Metas de convocatoria'!G60 -> 30 | F54: =ROUND(('Metas de convocatoria'!$C$14+(E$18-12*'Metas de convocatoria'!$C$14)*$C54/SUM($C$53:$C$64))/5,0)*5 -> 35 | G54: =F54-D54 -> 10 | H54: Piso + reparto proporcional al peso.
A55: Mesas Sectoriales | B55: ='Metas de convocatoria'!B61 -> Salud | C55: ='Metas de convocatoria'!E61 -> 2.4494897 | D55: =ROUND(('Metas de convocatoria'!$C$14+(C$18-12*'Metas de convocatoria'!$C$14)*$C55/SUM($C$53:$C$64))/5,0)*5 -> 25 | E55: ='Metas de convocatoria'!G61 -> 30 | F55: =ROUND(('Metas de convocatoria'!$C$14+(E$18-12*'Metas de convocatoria'!$C$14)*$C55/SUM($C$53:$C$64))/5,0)*5 -> 35 | G55: =F55-D55 -> 10 | H55: Piso + reparto proporcional al peso.
A56: Mesas Sectoriales | B56: ='Metas de convocatoria'!B62 -> Educacion | C56: ='Metas de convocatoria'!E62 -> 3.8729833 | D56: =ROUND(('Metas de convocatoria'!$C$14+(C$18-12*'Metas de convocatoria'!$C$14)*$C56/SUM($C$53:$C$64))/5,0)*5 -> 30 | E56: ='Metas de convocatoria'!G62 -> 35 | F56: =ROUND(('Metas de convocatoria'!$C$14+(E$18-12*'Metas de convocatoria'!$C$14)*$C56/SUM($C$53:$C$64))/5,0)*5 -> 40 | G56: =F56-D56 -> 10 | H56: Piso + reparto proporcional al peso.
A57: Mesas Sectoriales | B57: ='Metas de convocatoria'!B63 -> Movilidad y Espacio Público | C57: ='Metas de convocatoria'!E63 -> 2.8284271 | D57: =ROUND(('Metas de convocatoria'!$C$14+(C$18-12*'Metas de convocatoria'!$C$14)*$C57/SUM($C$53:$C$64))/5,0)*5 -> 25 | E57: ='Metas de convocatoria'!G63 -> 30 | F57: =ROUND(('Metas de convocatoria'!$C$14+(E$18-12*'Metas de convocatoria'!$C$14)*$C57/SUM($C$53:$C$64))/5,0)*5 -> 35 | G57: =F57-D57 -> 10 | H57: Piso + reparto proporcional al peso.
A58: Mesas Sectoriales | B58: ='Metas de convocatoria'!B64 -> Servicios públicos, infraestructura y vivienda | C58: ='Metas de convocatoria'!E64 -> 3.3166248 | D58: =ROUND(('Metas de convocatoria'!$C$14+(C$18-12*'Metas de convocatoria'!$C$14)*$C58/SUM($C$53:$C$64))/5,0)*5 -> 25 | E58: ='Metas de convocatoria'!G64 -> 35 | F58: =ROUND(('Metas de convocatoria'!$C$14+(E$18-12*'Metas de convocatoria'!$C$14)*$C58/SUM($C$53:$C$64))/5,0)*5 -> 40 | G58: =F58-D58 -> 15 | H58: Piso + reparto proporcional al peso.
A59: Mesas Sectoriales | B59: ='Metas de convocatoria'!B65 -> Seguridad y Convivencia Ciudadana | C59: ='Metas de convocatoria'!E65 -> 6.164414 | D59: =C$18-(SUM(D53:D58)+SUM(D60:D64)) -> 35 | E59: ='Metas de convocatoria'!G65 -> 40 | F59: =E$18-(SUM(F53:F58)+SUM(F60:F64)) -> 50 | G59: =F59-D59 -> 15 | H59: Fila de ajuste: absorbe el redondeo para que el bloque cuadre.
A60: Mesas Sectoriales | B60: ='Metas de convocatoria'!B66 -> Medio ambiente, Gestión del riesgo y Planeación | C60: ='Metas de convocatoria'!E66 -> 4.8989795 | D60: =ROUND(('Metas de convocatoria'!$C$14+(C$18-12*'Metas de convocatoria'!$C$14)*$C60/SUM($C$53:$C$64))/5,0)*5 -> 30 | E60: ='Metas de convocatoria'!G66 -> 40 | F60: =ROUND(('Metas de convocatoria'!$C$14+(E$18-12*'Metas de convocatoria'!$C$14)*$C60/SUM($C$53:$C$64))/5,0)*5 -> 50 | G60: =F60-D60 -> 20 | H60: Piso + reparto proporcional al peso.
A61: Mesas Sectoriales | B61: ='Metas de convocatoria'!B67 -> Desarrollo económico, Turismo / Competitividad , ciencia y tecnología | C61: ='Metas de convocatoria'!E67 -> 5.2915026 | D61: =ROUND(('Metas de convocatoria'!$C$14+(C$18-12*'Metas de convocatoria'!$C$14)*$C61/SUM($C$53:$C$64))/5,0)*5 -> 30 | E61: ='Metas de convocatoria'!G67 -> 40 | F61: =ROUND(('Metas de convocatoria'!$C$14+(E$18-12*'Metas de convocatoria'!$C$14)*$C61/SUM($C$53:$C$64))/5,0)*5 -> 50 | G61: =F61-D61 -> 20 | H61: Piso + reparto proporcional al peso.
A62: Mesas Sectoriales | B62: ='Metas de convocatoria'!B68 -> Transparencia y Cultura Ciudadana | C62: ='Metas de convocatoria'!E68 -> 5.9160798 | D62: =ROUND(('Metas de convocatoria'!$C$14+(C$18-12*'Metas de convocatoria'!$C$14)*$C62/SUM($C$53:$C$64))/5,0)*5 -> 30 | E62: ='Metas de convocatoria'!G68 -> 45 | F62: =ROUND(('Metas de convocatoria'!$C$14+(E$18-12*'Metas de convocatoria'!$C$14)*$C62/SUM($C$53:$C$64))/5,0)*5 -> 55 | G62: =F62-D62 -> 25 | H62: Piso + reparto proporcional al peso.
A63: Mesas Sectoriales | B63: ='Metas de convocatoria'!B69 -> Mesa de Construcción de Paz | C63: ='Metas de convocatoria'!E69 -> 4.1231056 | D63: =ROUND(('Metas de convocatoria'!$C$14+(C$18-12*'Metas de convocatoria'!$C$14)*$C63/SUM($C$53:$C$64))/5,0)*5 -> 30 | E63: ='Metas de convocatoria'!G69 -> 35 | F63: =ROUND(('Metas de convocatoria'!$C$14+(E$18-12*'Metas de convocatoria'!$C$14)*$C63/SUM($C$53:$C$64))/5,0)*5 -> 45 | G63: =F63-D63 -> 15 | H63: Piso + reparto proporcional al peso.
A64: Mesas Sectoriales | B64: ='Metas de convocatoria'!B70 -> Seguridad alimentaria (nueva) | C64: ='Metas de convocatoria'!E70 -> 2.236068 | D64: =ROUND(('Metas de convocatoria'!$C$14+(C$18-12*'Metas de convocatoria'!$C$14)*$C64/SUM($C$53:$C$64))/5,0)*5 -> 25 | E64: ='Metas de convocatoria'!G70 -> 30 | F64: =ROUND(('Metas de convocatoria'!$C$14+(E$18-12*'Metas de convocatoria'!$C$14)*$C64/SUM($C$53:$C$64))/5,0)*5 -> 35 | G64: =F64-D64 -> 10 | H64: Piso + reparto proporcional al peso.
A65: Subtotal Sectoriales | D65: =SUM(D53:D64) -> 335 | E65: =SUM(E53:E64) -> 420 | F65: =SUM(F53:F64) -> 505 | G65: =SUM(G53:G64) -> 170
A67: TOTAL DE PERSONAS (35 mesas) | D67: =D27+D40+D51+D65 -> 2000 | E67: =E27+E40+E51+E65 -> 2500 | F67: =F27+F40+F51+F65 -> 3000 | G67: =G27+G40+G51+G65 -> 1000
A68: Diferencia frente al escenario (debe ser 0) | D68: =D67-$C$7 -> 0 | E68: =E67-$C$5 -> 0 | F68: =F67-$C$8 -> 0
A70: NOTAS DE LA PROYECCIÓN
A71: 1. El margen de ±500 personas (±20%) es un parámetro fijado por el equipo, no un error muestral: indica el rango de asistencia que se planea atender, no una estimación estadística.
A72: 2. Las metas de bloque se escalan por igual (×0,8 y ×1,2) y se redondean a múltiplos de 5; el bloque sectorial es el saldo para que cada escenario sume exactamente 2.000, 2.500 o 3.000.
A73: 3. Los pisos mínimos por mesa (20 rurales, 30 poblacionales, 20 sectoriales) se mantienen en los tres escenarios; por eso en el escenario mínimo las mesas pequeñas bajan menos que el 20%.
A74: 4. Hereda las limitaciones de la hoja "Metas de convocatoria": población de Bayunca estimada, Tierra Bomba provisional, poblaciones de corregimientos sin año en la fuente (POT) y cifras LGTBI/étnicas por autorreconocimiento.
A75: 5. Uso sugerido: logística (espacio, refrigerios, materiales) con el escenario máximo; meta de asistencia con el central; umbral de validez de la mesa con el mínimo.

Sheet Detalle por mesa
A1: Clasificación | B1: Mesa | C1: Código | D1: Actor / dependencia | E1: Tipo | F1: Sector | G1: Rol en la mesa | H1: Dimensión (condición) en la matriz | I1: Eje transversal Crisis | J1: Aporte en la matriz | K1: Criterio de asignación a la mesa
A2: Mesas Territoriales | B2: Localidad Histórica y del Caribe Norte | C2: Dependencia | D2: Alcaldías Locales 1, 2 y 3 | E2: Territorial | F2: Público | G2: Principal | H2: Comunitaria (Principal); Personal (Secundario) | I2: Secundario | J2: Dependencia distrital ya registrada en la matriz. | K2: Base territorial + Centro Histórico (nombre de la localidad / texto de la matriz) — validar
A3: Mesas Territoriales | B3: Localidad Histórica y del Caribe Norte | C3: Dependencia | D3: Instituto Distrital de Acción Comunal (IDACC) | E3: Descentralizado | F3: Público | G3: Principal | H3: Comunitaria (Principal); Política (Secundario) | I3: — | J3: Dependencia distrital ya registrada en la matriz. | K3: Base territorial + Centro Histórico (nombre de la localidad / texto de la matriz) — validar
A4: Mesas Territoriales | B4: Localidad Histórica y del Caribe Norte | C4: Dependencia | D4: Instituto de Patrimonio y Cultura de Cartagena (IPCC) | E4: Descentralizado | F4: Público | G4: Principal | H4: Comunitaria (Principal); Económica (Secundario) | I4: — | J4: Dependencia distrital ya registrada en la matriz. | K4: Base territorial + Centro Histórico (nombre de la localidad / texto de la matriz) — validar
A5: Mesas Territoriales | B5: Localidad Histórica y del Caribe Norte | C5: Dependencia | D5: Secretaría de Participación y Desarrollo Social (SPD/UMATA) | E5: Secretaría | F5: Público | G5: Principal | H5: Comunitaria (Principal); Económica (Secundario); Alimentaria (Secundario) | I5: — | J5: Dependencia distrital ya registrada en la matriz. | K5: Base territorial + Centro Histórico (nombre de la localidad / texto de la matriz) — validar
A6: Mesas Territoriales | B6: Localidad Histórica y del Caribe Norte | C6: COM-01 | D6: Asociaciones de Juntas de Acción Comunal (ASOJAC) | E6: Comunitario | F6: Social | G6: Principal | H6: Comunitaria (Principal); Política (Secundario) | I6: — | J6: Conocimiento del territorio, convocatoria comunitaria, priorización de problemas. | K6: Base territorial + Centro Histórico (nombre de la localidad / texto de la matriz) — validar
A7: Mesas Territoriales | B7: Localidad Histórica y del Caribe Norte | C7: PRI-03 | D7: Asociación de Comerciantes del Centro Histórico | E7: Sector Privado | F7: Privado | G7: Principal | H7: Económica (Secundario); Personal (Principal) | I7: — | J7: Datos de hurto a comercios, extorsión, percepción de inseguridad. | K7: Base territorial + Centro Histórico (nombre de la localidad / texto de la matriz) — validar
A8: Mesas Territoriales | B8: Localidad Histórica y del Caribe Norte | C8: PRI-08 | D8: Asociación de Dueños de Bares y Discotecas (Centro Histórico) | E8: Sector Privado | F8: Privado | G8: Principal | H8: Comunitaria (Secundario); Personal (Principal) | I8: — | J8: Datos de seguridad en la economía nocturna, convivencia, violencia. | K8: Base territorial + Centro Histórico (nombre de la localidad / texto de la matriz) — validar
A9: Mesas Territoriales | B9: Localidad Histórica y del Caribe Norte | C9: COM-04 | D9: Líderes sociales y comunitarios (barrios en vulnerabilidad) | E9: Comunitario | F9: Social | G9: Principal | H9: Comunitaria (Principal) | I9: — | J9: Conocimiento profundo del territorio, confianza comunitaria, identificación de riesgos. | K9: Base territorial + Centro Histórico (nombre de la localidad / texto de la matriz) — validar
A10: Mesas Territoriales | B10: Localidad Histórica y del Caribe Norte | C10: ACA-11 | D10: Universidad de Bellas Artes | E10: Académico | F10: Social | G10: Principal | H10: Comunitaria (Principal) | I10: — | J10: Investigación, datos, estudios de seguridad. | K10: Base territorial + Centro Histórico (nombre de la localidad / texto de la matriz) — validar
A11: Mesas Territoriales | B11: Localidad Histórica y del Caribe Norte | C11: Dependencia | D11: Gerencia de Espacio Público y Movilidad (GEPM) | E11: Gerencia | F11: Público | G11: Secundario | H11: Comunitaria (Secundario); Económica (Principal); Personal (Secundario) | I11: — | J11: Dependencia distrital ya registrada en la matriz. | K11: Apoyo territorial
A12: Mesas Territoriales | B12: Localidad Histórica y del Caribe Norte | C12: Dependencia | D12: Secretaría de Interior y Convivencia Ciudadana (SICC) | E12: Secretaría | F12: Público | G12: Secundario | H12: Personal (Principal); Política (Secundario) | I12: Secundario | J12: Dependencia distrital ya registrada en la matriz. | K12: Apoyo territorial
... A60: Mesas Rurales | B60: Boquilla | C60: COM-14 | D60: Líderes de corregimientos (Pasacaballos, Bayunca, etc.) | E60: Comunitario | F60: Social | G60: Principal | H60: Comunitaria (Principal); Ambiental (Secundario) | I60: — | J60: Visión rural, acceso a servicios, riesgos ambientales. | K60: Base rural: liderazgo territorial y riesgos ambientales (COM-14/15)
A61: Mesas Rurales | B61: Boquilla | C61: Dependencia | D61: CARDIQUE | E61: Descentralizado | F61: Público | G61: Secundario | H61: Ambiental (Principal) | I61: — | K61: Apoyo ambiental / gestión del riesgo / seguridad marítima
A62: Mesas Rurales | B62: Boquilla | C62: Dependencia | D62: EPA Cartagena | E62: Descentralizado | F62: Público | G62: Secundario | H62: Ambiental (Principal) | I62: — | J62: Dependencia distrital ya registrada en la matriz. | K62: Apoyo ambiental / gestión del riesgo / seguridad marítima
A63: Mesas Rurales | B63: Boquilla | C63: Dependencia | D63: Oficina para la Gestión del Riesgo y Desastres (OAGRD) | E63: Oficina / Unidad asesora | F63: Público | G63: Secundario | H63: Ambiental (Secundario) | I63: Principal | J63: Dependencia distrital ya registrada en la matriz. | K63: Apoyo ambiental / gestión del riesgo / seguridad marítima
A64: Mesas Rurales | B64: Boquilla | C64: Dependencia | D64: Secretaría de Infraestructura | E64: Secretaría | F64: Público | G64: Secundario | H64: Ambiental (Principal); Salud y sanitaria (Secundario) | I64: — | J64: Dependencia distrital ya registrada en la matriz. | K64: Apoyo ambiental / gestión del riesgo / seguridad marítima
A65: Mesas Rurales | B65: Boquilla | C65: FUE-05 | D65: Dirección General Marítima (DIMAR) | E65: Fuerza Pública | F65: Público | G65: Secundario | H65: Ambiental (Principal) | I65: Secundario | J65: Datos sobre seguridad marítima, riesgos costeros, movilidad marítima y protección del territorio marino-costero. | K65: Apoyo ambiental / gestión del riesgo / seguridad marítima
A66: Mesas Rurales | B66: Boquilla | C66: SOC-07 | D66: Fundación Ecovida | E66: Sector Social | F66: Social | G66: Secundario | H66: Comunitaria (Secundario); Ambiental (Principal) | I66: — | J66: Riesgos ambientales, desarrollo sostenible. | K66: Apoyo ambiental / gestión del riesgo / seguridad marítima
A67: Mesas Rurales | B67: Boquilla | C67: FUE-06 | D67: Policía Metropolitana de Cartagena | E67: Fuerza Pública | F67: Público | G67: Secundario | H67: Comunitaria (Secundario); Personal (Principal) | I67: Secundario | J67: Datos de delitos, operativos, mapas de criminalidad, inteligencia e informes sobre los diferentes tipos de violencia en un periodo de los últimos 5 años. | K67: Apoyo ambiental / gestión del riesgo / seguridad marítima
A68: Mesas Rurales | B68: Arroyo de Piedra | C68: Dependencia | D68: Alcaldías Locales 1, 2 y 3 | E68: Territorial | F68: Público | G68: Principal | H68: Comunitaria (Principal); Personal (Secundario) | I68: Secundario | J68: Dependencia distrital ya registrada en la matriz. | K68: Base rural: liderazgo territorial y riesgos ambientales (COM-14/15)
A69: Mesas Rurales | B69: Arroyo de Piedra | C69: Dependencia | D69: Instituto Distrital de Acción Comunal (IDACC) | E69: Descentralizado | F69: Público | G69: Principal | H69: Comunitaria (Principal); Política (Secundario) | I69: — | J69: Dependencia distrital ya registrada en la matriz. | K69: Base rural: liderazgo territorial y riesgos ambientales (COM-14/15)
A70: Mesas Rurales | B70: Arroyo de Piedra | C70: Dependencia | D70: Secretaría de Participación y Desarrollo Social (SPD/UMATA) | E70: Secretaría | F70: Público | G70: Principal | H70: Comunitaria (Principal); Económica (Secundario); Alimentaria (Secundario) | I70: — | J70: Dependencia distrital ya registrada en la matriz. | K70: Base rural: liderazgo territorial y riesgos ambientales (COM-14/15)
A71: Mesas Rurales | B71: Arroyo de Piedra | C71: COM-01 | D71: Asociaciones de Juntas de Acción Comunal (ASOJAC) | E71: Comunitario | F71: Social | G71: Principal | H71: Comunitaria (Principal); Política (Secundario) | I71: — | J71: Conocimiento del territorio, convocatoria comunitaria, priorización de problemas. | K71: Base rural: liderazgo territorial y riesgos ambientales (COM-14/15)
A72: Mesas Rurales | B72: Arroyo de Piedra | C72: COM-14 | D72: Líderes de corregimientos (Pasacaballos, Bayunca, etc.) | E72: Comunitario | F72: Social | G72: Principal | H72: Comunitaria (Principal); Ambiental (Secundario) | I72: — | J72: Visión rural, acceso a servicios, riesgos ambientales. | K72: Base rural: liderazgo territorial y riesgos ambientales (COM-14/15)
A73: Mesas Rurales | B73: Arroyo de Piedra | C73: Dependencia | D73: CARDIQUE | E73: Descentralizado | F73: Público | G73: Secundario | H73: Ambiental (Principal) | I73: — | K73: Apoyo ambiental / gestión del riesgo / seguridad marítima
A74: Mesas Rurales | B74: Arroyo de Piedra | C74: Dependencia | D74: EPA Cartagena | E74: Descentralizado | F74: Público | G74: Secundario | H74: Ambiental (Principal) | I74: — | J74: Dependencia distrital ya registrada en la matriz. | K74: Apoyo ambiental / gestión del riesgo / seguridad marítima
A75: Mesas Rurales | B75: Arroyo de Piedra | C75: Dependencia | D75: Oficina para la Gestión del Riesgo y Desastres (OAGRD) | E75: Oficina / Unidad asesora | F75: Público | G75: Secundario | H75: Ambiental (Secundario) | I75: Principal | J75: Dependencia distrital ya registrada en la matriz. | K75: Apoyo ambiental / gestión del riesgo / seguridad marítima
A76: Mesas Rurales | B76: Arroyo de Piedra | C76: Dependencia | D76: Secretaría de Infraestructura | E76: Secretaría | F76: Público | G76: Secundario | H76: Ambiental (Principal); Salud y sanitaria (Secundario) | I76: — | J76: Dependencia distrital ya registrada en la matriz. | K76: Apoyo ambiental / gestión del riesgo / seguridad marítima
A77: Mesas Rurales | B77: Arroyo de Piedra | C77: FUE-05 | D77: Dirección General Marítima (DIMAR) | E77: Fuerza Pública | F77: Público | G77: Secundario | H77: Ambiental (Principal) | I77: Secundario | J77: Datos sobre seguridad marítima, riesgos costeros, movilidad marítima y protección del territorio marino-costero. | K77: Apoyo ambiental / gestión del riesgo / seguridad marítima
A78: Mesas Rurales | B78: Arroyo de Piedra | C78: SOC-07 | D78: Fundación Ecovida | E78: Sector Social | F78: Social | G78: Secundario | H78: Comunitaria (Secundario); Ambiental (Principal) | I78: — | J78: Riesgos ambientales, desarrollo sostenible. | K78: Apoyo ambiental / gestión del riesgo / seguridad marítima
A79: Mesas Rurales | B79: Arroyo de Piedra | C79: FUE-06 | D79: Policía Metropolitana de Cartagena | E79: Fuerza Pública | F79: Público | G79: Secundario | H79: Comunitaria (Secundario); Personal (Principal) | I79: Secundario | J79: Datos de delitos, operativos, mapas de criminalidad, inteligencia e informes sobre los diferentes tipos de violencia en un periodo de los últimos 5 años. | K79: Apoyo ambiental / gestión del riesgo / seguridad marítima
A80: Mesas Rurales | B80: Punta Canoa | C80: Dependencia | D80: Alcaldías Locales 1, 2 y 3 | E80: Territorial | F80: Público | G80: Principal | H80: Comunitaria (Principal); Personal (Secundario) | I80: Secundario | J80: Dependencia distrital ya registrada en la matriz. | K80: Base rural: liderazgo territorial y riesgos ambientales (COM-14/15)
A81: Mesas Rurales | B81: Punta Canoa | C81: Dependencia | D81: Instituto Distrital de Acción Comunal (IDACC) | E81: Descentralizado | F81: Público | G81: Principal | H81: Comunitaria (Principal); Política (Secundario) | I81: — | J81: Dependencia distrital ya registrada en la matriz. | K81: Base rural: liderazgo territorial y riesgos ambientales (COM-14/15)
A82: Mesas Rurales | B82: Punta Canoa | C82: Dependencia | D82: Secretaría de Participación y Desarrollo Social (SPD/UMATA) | E82: Secretaría | F82: Público | G82: Principal | H82: Comunitaria (Principal); Económica (Secundario); Alimentaria (Secundario) | I82: — | J82: Dependencia distrital ya registrada en la matriz. | K82: Base rural: liderazgo territorial y riesgos ambientales (COM-14/15)
A83: Mesas Rurales | B83: Punta Canoa | C83: COM-01 | D83: Asociaciones de Juntas de Acción Comunal (ASOJAC) | E83: Comunitario | F83: Social | G83: Principal | H83: Comunitaria (Principal); Política (Secundario) | I83: — | J83: Conocimiento del territorio, convocatoria comunitaria, priorización de problemas. | K83: Base rural: liderazgo territorial y riesgos ambientales (COM-14/15)
A84: Mesas Rurales | B84: Punta Canoa | C84: COM-14 | D84: Líderes de corregimientos (Pasacaballos, Bayunca, etc.) | E84: Comunitario | F84: Social | G84: Principal | H84: Comunitaria (Principal); Ambiental (Secundario) | I84: — | J84: Visión rural, acceso a servicios, riesgos ambientales. | K84: Base rural: liderazgo territorial y riesgos ambientales (COM-14/15)
A85: Mesas Rurales | B85: Punta Canoa | C85: Dependencia | D85: CARDIQUE | E85: Descentralizado | F85: Público | G85: Secundario | H85: Ambiental (Principal) | I85: — | K85: Apoyo ambiental / gestión del riesgo / seguridad marítima
A86: Mesas Rurales | B86: Punta Canoa | C86: Dependencia | D86: EPA Cartagena | E86: Descentralizado | F86: Público | G86: Secundario | H86: Ambiental (Principal) | I86: — | J86: Dependencia distrital ya registrada en la matriz. | K86: Apoyo ambiental / gestión del riesgo / seguridad marítima
A87: Mesas Rurales | B87: Punta Canoa | C87: Dependencia | D87: Oficina para la Gestión del Riesgo y Desastres (OAGRD) | E87: Oficina / Unidad asesora | F87: Público | G87: Secundario | H87: Ambiental (Secundario) | I87: Principal | J87: Dependencia distrital ya registrada en la matriz. | K87: Apoyo ambiental / gestión del riesgo / seguridad marítima
A88: Mesas Rurales | B88: Punta Canoa | C88: Dependencia | D88: Secretaría de Infraestructura | E88: Secretaría | F88: Público | G88: Secundario | H88: Ambiental (Principal); Salud y sanitaria (Secundario) | I88: — | J88: Dependencia distrital ya registrada en la matriz. | K88: Apoyo ambiental / gestión del riesgo / seguridad marítima
A89: Mesas Rurales | B89: Punta Canoa | C89: FUE-05 | D89: Dirección General Marítima (DIMAR) | E89: Fuerza Pública | F89: Público | G89: Secundario | H89: Ambiental (Principal) | I89: Secundario | J89: Datos sobre seguridad marítima, riesgos costeros, movilidad marítima y protección del territorio marino-costero. | K89: Apoyo ambiental / gestión del riesgo / seguridad marítima
A90: Mesas Rurales | B90: Punta Canoa | C90: SOC-07 | D90: Fundación Ecovida | E90: Sector Social | F90: Social | G90: Secundario | H90: Comunitaria (Secundario); Ambiental (Principal) | I90: — | J90: Riesgos ambientales, desarrollo sostenible. | K90: Apoyo ambiental / gestión del riesgo / seguridad marítima
A91: Mesas Rurales | B91: Punta Canoa | C91: FUE-06 | D91: Policía Metropolitana de Cartagena | E91: Fuerza Pública | F91: Público | G91: Secundario | H91: Comunitaria (Secundario); Personal (Principal) | I91: Secundario | J91: Datos de delitos, operativos, mapas de criminalidad, inteligencia e informes sobre los diferentes tipos de violencia en un periodo de los últimos 5 años. | K91: Apoyo ambiental / gestión del riesgo / seguridad marítima
A92: Mesas Rurales | B92: Bayunca | C92: Dependencia | D92: Alcaldías Locales 1, 2 y 3 | E92: Territorial | F92: Público | G92: Principal | H92: Comunitaria (Principal); Personal (Secundario) | I92: Secundario | J92: Dependencia distrital ya registrada en la matriz. | K92: Base rural: liderazgo territorial y riesgos ambientales (COM-14/15)
A93: Mesas Rurales | B93: Bayunca | C93: Dependencia | D93: Instituto Distrital de Acción Comunal (IDACC) | E93: Descentralizado | F93: Público | G93: Principal | H93: Comunitaria (Principal); Política (Secundario) | I93: — | J93: Dependencia distrital ya registrada en la matriz. | K93: Base rural: liderazgo territorial y riesgos ambientales (COM-14/15)
A94: Mesas Rurales | B94: Bayunca | C94: Dependencia | D94: Secretaría de Participación y Desarrollo Social (SPD/UMATA) | E94: Secretaría | F94: Público | G94: Principal | H94: Comunitaria (Principal); Económica (Secundario); Alimentaria (Secundario) | I94: — | J94: Dependencia distrital ya registrada en la matriz. | K94: Base rural: liderazgo territorial y riesgos ambientales (COM-14/15)
A95: Mesas Rurales | B95: Bayunca | C95: COM-01 | D95: Asociaciones de Juntas de Acción Comunal (ASOJAC) | E95: Comunitario | F95: Social | G95: Principal | H95: Comunitaria (Principal); Política (Secundario) | I95: — | J95: Conocimiento del territorio, convocatoria comunitaria, priorización de problemas. | K95: Base rural: liderazgo territorial y riesgos ambientales (COM-14/15)
A96: Mesas Rurales | B96: Bayunca | C96: COM-14 | D96: Líderes de corregimientos (Pasacaballos, Bayunca, etc.) | E96: Comunitario | F96: Social | G96: Principal | H96: Comunitaria (Principal); Ambiental (Secundario) | I96: — | J96: Visión rural, acceso a servicios, riesgos ambientales. | K96: Base rural: liderazgo territorial y riesgos ambientales (COM-14/15)
A97: Mesas Rurales | B97: Bayunca | C97: Dependencia | D97: CARDIQUE | E97: Descentralizado | F97: Público | G97: Secundario | H97: Ambiental (Principal) | I97: — | K97: Apoyo ambiental / gestión del riesgo / seguridad marítima
A98: Mesas Rurales | B98: Bayunca | C98: Dependencia | D98: EPA Cartagena | E98: Descentralizado | F98: Público | G98: Secundario | H98: Ambiental (Principal) | I98: — | J98: Dependencia distrital ya registrada en la matriz. | K98: Apoyo ambiental / gestión del riesgo / seguridad marítima
A99: Mesas Rurales | B99: Bayunca | C99: Dependencia | D99: Oficina para la Gestión del Riesgo y Desastres (OAGRD) | E99: Oficina / Unidad asesora | F99: Público | G99: Secundario | H99: Ambiental (Secundario) | I99: Principal | J99: Dependencia distrital ya registrada en la matriz. | K99: Apoyo ambiental / gestión del riesgo / seguridad marítima
A100: Mesas Rurales | B100: Bayunca | C100: Dependencia | D100: Secretaría de Infraestructura | E100: Secretaría | F100: Público | G100: Secundario | H100: Ambiental (Principal); Salud y sanitaria (Secundario) | I100: — | J100: Dependencia distrital ya registrada en la matriz. | K100: Apoyo ambiental / gestión del riesgo / seguridad marítima
A101: Mesas Rurales | B101: Bayunca | C101: SOC-07 | D101: Fundación Ecovida | E101: Sector Social | F101: Social | G101: Secundario | H101: Comunitaria (Secundario); Ambiental (Principal) | I101: — | J101: Riesgos ambientales, desarrollo sostenible. | K101: Apoyo ambiental / gestión del riesgo / seguridad marítima
A102: Mesas Rurales | B102: Bayunca | C102: FUE-06 | D102: Policía Metropolitana de Cartagena | E102: Fuerza Pública | F102: Público | G102: Secundario | H102: Comunitaria (Secundario); Personal (Principal) | I102: Secundario | J102: Datos de delitos, operativos, mapas de criminalidad, inteligencia e informes sobre los diferentes tipos de violencia en un periodo de los últimos 5 años. | K102: Apoyo ambiental / gestión del riesgo / seguridad marítima
A103: Mesas Rurales | B103: Pasacaballos | C103: Dependencia | D103: Alcaldías Locales 1, 2 y 3 | E103: Territorial | F103: Público | G103: Principal | H103: Comunitaria (Principal); Personal (Secundario) | I103: Secundario | J103: Dependencia distrital ya registrada en la matriz. | K103: Base rural: liderazgo territorial y riesgos ambientales (COM-14/15)
A104: Mesas Rurales | B104: Pasacaballos | C104: Dependencia | D104: Instituto Distrital de Acción Comunal (IDACC) | E104: Descentralizado | F104: Público | G104: Principal | H104: Comunitaria (Principal); Política (Secundario) | I104: — | J104: Dependencia distrital ya registrada en la matriz. | K104: Base rural: liderazgo territorial y riesgos ambientales (COM-14/15)
A105: Mesas Rurales | B105: Pasacaballos | C105: Dependencia | D105: Secretaría de Participación y Desarrollo Social (SPD/UMATA) | E105: Secretaría | F105: Público | G105: Principal | H105: Comunitaria (Principal); Económica (Secundario); Alimentaria (Secundario) | I105: — | J105: Dependencia distrital ya registrada en la matriz. | K105: Base rural: liderazgo territorial y riesgos ambientales (COM-14/15)
A106: Mesas Rurales | B106: Pasacaballos | C106: COM-01 | D106: Asociaciones de Juntas de Acción Comunal (ASOJAC) | E106: Comunitario | F106: Social | G106: Principal | H106: Comunitaria (Principal); Política (Secundario) | I106: — | J106: Conocimiento del territorio, convocatoria comunitaria, priorización de problemas. | K106: Base rural: liderazgo territorial y riesgos ambientales (COM-14/15)
A107: Mesas Rurales | B107: Pasacaballos | C107: COM-08 | D107: Consejo Comunitario de la Comunidad Negra de Pasacaballos | E107: Comunitario | F107: Social | G107: Principal | H107: Comunitaria (Principal) | I107: — | J107: Visión étnica, territorial. | K107: Base rural: liderazgo territorial y riesgos ambientales (COM-14/15)
A108: Mesas Rurales | B108: Pasacaballos | C108: COM-14 | D108: Líderes de corregimientos (Pasacaballos, Bayunca, etc.) | E108: Comunitario | F108: Social | G108: Principal | H108: Comunitaria (Principal); Ambiental (Secundario) | I108: — | J108: Visión rural, acceso a servicios, riesgos ambientales. | K108: Base rural: liderazgo territorial y riesgos ambientales (COM-14/15)
A109: Mesas Rurales | B109: Pasacaballos | C109: Dependencia | D109: CARDIQUE | E109: Descentralizado | F109: Público | G109: Secundario | H109: Ambiental (Principal) | I109: — | K109: Apoyo ambiental / gestión del riesgo / seguridad marítima
A110: Mesas Rurales | B110: Pasacaballos | C110: Dependencia | D110: EPA Cartagena | E110: Descentralizado | F110: Público | G110: Secundario | H110: Ambiental (Principal) | I110: — | J110: Dependencia distrital ya registrada en la matriz. | K110: Apoyo ambiental / gestión del riesgo / seguridad marítima
A111: Mesas Rurales | B111: Pasacaballos | C111: Dependencia | D111: Oficina para la Gestión del Riesgo y Desastres (OAGRD) | E111: Oficina / Unidad asesora | F111: Público | G111: Secundario | H111: Ambiental (Secundario) | I111: Principal | J111: Dependencia distrital ya registrada en la matriz. | K111: Apoyo ambiental / gestión del riesgo / seguridad marítima
A112: Mesas Rurales | B112: Pasacaballos | C112: Dependencia | D112: Secretaría de Infraestructura | E112: Secretaría | F112: Público | G112: Secundario | H112: Ambiental (Principal); Salud y sanitaria (Secundario) | I112: — | J112: Dependencia distrital ya registrada en la matriz. | K112: Apoyo ambiental / gestión del riesgo / seguridad marítima
A113: Mesas Rurales | B113: Pasacaballos | C113: SOC-07 | D113: Fundación Ecovida | E113: Sector Social | F113: Social | G113: Secundario | H113: Comunitaria (Secundario); Ambiental (Principal) | I113: — | J113: Riesgos ambientales, desarrollo sostenible. | K113: Apoyo ambiental / gestión del riesgo / seguridad marítima
A114: Mesas Rurales | B114: Pasacaballos | C114: FUE-06 | D114: Policía Metropolitana de Cartagena | E114: Fuerza Pública | F114: Público | G114: Secundario | H114: Comunitaria (Secundario); Personal (Principal) | I114: Secundario | J114: Datos de delitos, operativos, mapas de criminalidad, inteligencia e informes sobre los diferentes tipos de violencia en un periodo de los últimos 5 años. | K114: Apoyo ambiental / gestión del riesgo / seguridad marítima
A115: Mesas Rurales | B115: Arroyo Grande | C115: Dependencia | D115: Alcaldías Locales 1, 2 y 3 | E115: Territorial | F115: Público | G115: Principal | H115: Comunitaria (Principal); Personal (Secundario) | I115: Secundario | J115: Dependencia distrital ya registrada en la matriz. | K115: Base rural: liderazgo territorial y riesgos ambientales (COM-14/15)
A116: Mesas Rurales | B116: Arroyo Grande | C116: Dependencia | D116: Instituto Distrital de Acción Comunal (IDACC) | E116: Descentralizado | F116: Público | G116: Principal | H116: Comunitaria (Principal); Política (Secundario) | I116: — | J116: Dependencia distrital ya registrada en la matriz. | K116: Base rural: liderazgo territorial y riesgos ambientales (COM-14/15)
A117: Mesas Rurales | B117: Arroyo Grande | C117: Dependencia | D117: Secretaría de Participación y Desarrollo Social (SPD/UMATA) | E117: Secretaría | F117: Público | G117: Principal | H117: Comunitaria (Principal); Económica (Secundario); Alimentaria (Secundario) | I117: — | J117: Dependencia distrital ya registrada en la matriz. | K117: Base rural: liderazgo territorial y riesgos ambientales (COM-14/15)
A118: Mesas Rurales | B118: Arroyo Grande | C118: COM-01 | D118: Asociaciones de Juntas de Acción Comunal (ASOJAC) | E118: Comunitario | F118: Social | G118: Principal | H118: Comunitaria (Principal); Política (Secundario) | I118: — | J118: Conocimiento del territorio, convocatoria comunitaria, priorización de problemas. | K118: Base rural: liderazgo territorial y riesgos ambientales (COM-14/15)
A119: Mesas Rurales | B119: Arroyo Grande | C119: COM-14 | D119: Líderes de corregimientos (Pasacaballos, Bayunca, etc.) | E119: Comunitario | F119: Social | G119: Principal | H119: Comunitaria (Principal); Ambiental (Secundario) | I119: — | J119: Visión rural, acceso a servicios, riesgos ambientales. | K119: Base rural: liderazgo territorial y riesgos ambientales (COM-14/15)
A120: Mesas Rurales | B120: Arroyo Grande | C120: Dependencia | D120: CARDIQUE | E120: Descentralizado | F120: Público | G120: Secundario | H120: Ambiental (Principal) | I120: — | K120: Apoyo ambiental / gestión del riesgo / seguridad marítima
A121: Mesas Rurales | B121: Arroyo Grande | C121: Dependencia | D121: EPA Cartagena | E121: Descentralizado | F121: Público | G121: Secundario | H121: Ambiental (Principal) | I121: — | J121: Dependencia distrital ya registrada en la matriz. | K121: Apoyo ambiental / gestión del riesgo / seguridad marítima
A122: Mesas Rurales | B122: Arroyo Grande | C122: Dependencia | D122: Oficina para la Gestión del Riesgo y Desastres (OAGRD) | E122: Oficina / Unidad asesora | F122: Público | G122: Secundario | H122: Ambiental (Secundario) | I122: Principal | J122: Dependencia distrital ya registrada en la matriz. | K122: Apoyo ambiental / gestión del riesgo / seguridad marítima
A123: Mesas Rurales | B123: Arroyo Grande | C123: Dependencia | D123: Secretaría de Infraestructura | E123: Secretaría | F123: Público | G123: Secundario | H123: Ambiental (Principal); Salud y sanitaria (Secundario) | I123: — | J123: Dependencia distrital ya registrada en la matriz. | K123: Apoyo ambiental / gestión del riesgo / seguridad marítima
A124: Mesas Rurales | B124: Arroyo Grande | C124: SOC-07 | D124: Fundación Ecovida | E124: Sector Social | F124: Social | G124: Secundario | H124: Comunitaria (Secundario); Ambiental (Principal) | I124: — | J124: Riesgos ambientales, desarrollo sostenible. | K124: Apoyo ambiental / gestión del riesgo / seguridad marítima
A125: Mesas Rurales | B125: Arroyo Grande | C125: FUE-06 | D125: Policía Metropolitana de Cartagena | E125: Fuerza Pública | F125: Público | G125: Secundario | H125: Comunitaria (Secundario); Personal (Principal) | I125: Secundario | J125: Datos de delitos, operativos, mapas de criminalidad, inteligencia e informes sobre los diferentes tipos de violencia en un periodo de los últimos 5 años. | K125: Apoyo ambiental / gestión del riesgo / seguridad marítima
A126: Mesas Rurales | B126: Santa Ana | C126: Dependencia | D126: Alcaldías Locales 1, 2 y 3 | E126: Territorial | F126: Público | G126: Principal | H126: Comunitaria (Principal); Personal (Secundario) | I126: Secundario | J126: Dependencia distrital ya registrada en la matriz. | K126: Base rural: liderazgo territorial y riesgos ambientales (COM-14/15)
A127: Mesas Rurales | B127: Santa Ana | C127: Dependencia | D127: Instituto Distrital de Acción Comunal (IDACC) | E127: Descentralizado | F127: Público | G127: Principal | H127: Comunitaria (Principal); Política (Secundario) | I127: — | J127: Dependencia distrital ya registrada en la matriz. | K127: Base rural: liderazgo territorial y riesgos ambientales (COM-14/15)
A128: Mesas Rurales | B128: Santa Ana | C128: Dependencia | D128: Secretaría de Participación y Desarrollo Social (SPD/UMATA) | E128: Secretaría | F128: Público | G128: Principal | H128: Comunitaria (Principal); Económica (Secundario); Alimentaria (Secundario) | I128: — | J128: Dependencia distrital ya registrada en la matriz. | K128: Base rural: liderazgo territorial y riesgos ambientales (COM-14/15)
A129: Mesas Rurales | B129: Santa Ana | C129: COM-01 | D129: Asociaciones de Juntas de Acción Comunal (ASOJAC) | E129: Comunitario | F129: Social | G129: Principal | H129: Comunitaria (Principal); Política (Secundario) | I129: — | J129: Conocimiento del territorio, convocatoria comunitaria, priorización de problemas. | K129: Base rural: liderazgo territorial y riesgos ambientales (COM-14/15)
A130: Mesas Rurales | B130: Santa Ana | C130: COM-07 | D130: Consejo Comunitario de la Comunidad Negra de la Isla de Barú | E130: Comunitario | F130: Social | G130: Principal | H130: Comunitaria (Principal) | I130: — | J130: Visión étnica, territorial, afectaciones específicas. | K130: Base rural: liderazgo territorial y riesgos ambientales (COM-14/15)
A131: Mesas Rurales | B131: Santa Ana | C131: COM-15 | D131: Líderes de Islas (Tierra Bomba, Barú, etc) | E131: Comunitario | F131: Social | G131: Principal | H131: Comunitaria (Principal); Ambiental (Secundario) | I131: — | J131: Visión insular, acceso a servicios, riesgos ambientales. | K131: Base rural: liderazgo territorial y riesgos ambientales (COM-14/15)
A132: Mesas Rurales | B132: Santa Ana | C132: Dependencia | D132: CARDIQUE | E132: Descentralizado | F132: Público | G132: Secundario | H132: Ambiental (Principal) | I132: — | K132: Apoyo ambiental / gestión del riesgo / seguridad marítima
A133: Mesas Rurales | B133: Santa Ana | C133: Dependencia | D133: EPA Cartagena | E133: Descentralizado | F133: Público | G133: Secundario | H133: Ambiental (Principal) | I133: — | J133: Dependencia distrital ya registrada en la matriz. | K133: Apoyo ambiental / gestión del riesgo / seguridad marítima
A134: Mesas Rurales | B134: Santa Ana | C134: Dependencia | D134: Oficina para la Gestión del Riesgo y Desastres (OAGRD) | E134: Oficina / Unidad asesora | F134: Público | G134: Secundario | H134: Ambiental (Secundario) | I134: Principal | J134: Dependencia distrital ya registrada en la matriz. | K134: Apoyo ambiental / gestión del riesgo / seguridad marítima
A135: Mesas Rurales | B135: Santa Ana | C135: Dependencia | D135: Secretaría de Infraestructura | E135: Secretaría | F135: Público | G135: Secundario | H135: Ambiental (Principal); Salud y sanitaria (Secundario) | I135: — | J135: Dependencia distrital ya registrada en la matriz. | K135: Apoyo ambiental / gestión del riesgo / seguridad marítima
A136: Mesas Rurales | B136: Santa Ana | C136: INS-30 | D136: Defensa Civil - Seccional Bolívar | E136: Institucional | F136: Público | G136: Secundario | H136: Ambiental (Secundario) | I136: Principal | J136: Datos sobre principales hechos de inseguridad damnificados, zonas de riesgo y principales emergencias atendidas (bajo qué factores). | K136: Apoyo ambiental / gestión del riesgo / seguridad marítima
A137: Mesas Rurales | B137: Santa Ana | C137: FUE-05 | D137: Dirección General Marítima (DIMAR) | E137: Fuerza Pública | F137: Público | G137: Secundario | H137: Ambiental (Principal) | I137: Secundario | J137: Datos sobre seguridad marítima, riesgos costeros, movilidad marítima y protección del territorio marino-costero. | K137: Apoyo ambiental / gestión del riesgo / seguridad marítima
A138: Mesas Rurales | B138: Santa Ana | C138: SOC-07 | D138: Fundación Ecovida | E138: Sector Social | F138: Social | G138: Secundario | H138: Comunitaria (Secundario); Ambiental (Principal) | I138: — | J138: Riesgos ambientales, desarrollo sostenible. | K138: Apoyo ambiental / gestión del riesgo / seguridad marítima
A139: Mesas Rurales | B139: Santa Ana | C139: FUE-01 | D139: Infantería de Marina (Armada Nacional) | E139: Fuerza Pública | F139: Público | G139: Secundario | H139: Personal (Principal) | I139: Secundario | J139: Datos respecto de microtráfico, extorsión, tráfico de migrantes y seguridad marítima. | K139: Apoyo ambiental / gestión del riesgo / seguridad marítima
A140: Mesas Rurales | B140: Santa Ana | C140: COM-14 | D140: Líderes de corregimientos (Pasacaballos, Bayunca, etc.) | E140: Comunitario | F140: Social | G140: Secundario | H140: Comunitaria (Principal); Ambiental (Secundario) | I140: — | J140: Visión rural, acceso a servicios, riesgos ambientales. | K140: Apoyo ambiental / gestión del riesgo / seguridad marítima
A141: Mesas Rurales | B141: Santa Ana | C141: FUE-06 | D141: Policía Metropolitana de Cartagena | E141: Fuerza Pública | F141: Público | G141: Secundario | H141: Comunitaria (Secundario); Personal (Principal) | I141: Secundario | J141: Datos de delitos, operativos, mapas de criminalidad, inteligencia e informes sobre los diferentes tipos de violencia en un periodo de los últimos 5 años. | K141: Apoyo ambiental / gestión del riesgo / seguridad marítima
A142: Mesas Rurales | B142: Tierra bomba | C142: Dependencia | D142: Alcaldías Locales 1, 2 y 3 | E142: Territorial | F142: Público | G142: Principal | H142: Comunitaria (Principal); Personal (Secundario) | I142: Secundario | J142: Dependencia distrital ya registrada en la matriz. | K142: Base rural: liderazgo territorial y riesgos ambientales (COM-14/15)
A143: Mesas Rurales | B143: Tierra bomba | C143: Dependencia | D143: Instituto Distrital de Acción Comunal (IDACC) | E143: Descentralizado | F143: Público | G143: Principal | H143: Comunitaria (Principal); Política (Secundario) | I143: — | J143: Dependencia distrital ya registrada en la matriz. | K143: Base rural: liderazgo territorial y riesgos ambientales (COM-14/15)
A144: Mesas Rurales | B144: Tierra bomba | C144: Dependencia | D144: Secretaría de Participación y Desarrollo Social (SPD/UMATA) | E144: Secretaría | F144: Público | G144: Principal | H144: Comunitaria (Principal); Económica (Secundario); Alimentaria (Secundario) | I144: — | J144: Dependencia distrital ya registrada en la matriz. | K144: Base rural: liderazgo territorial y riesgos ambientales (COM-14/15)
... A146: Mesas Rurales | B146: Tierra bomba | C146: COM-15 | D146: Líderes de Islas (Tierra Bomba, Barú, etc) | E146: Comunitario | F146: Social | G146: Principal | H146: Comunitaria (Principal); Ambiental (Secundario) | I146: — | J146: Visión insular, acceso a servicios, riesgos ambientales. | K146: Base rural: liderazgo territorial y riesgos ambientales (COM-14/15)
A147: Mesas Rurales | B147: Tierra bomba | C147: Dependencia | D147: CARDIQUE | E147: Descentralizado | F147: Público | G147: Secundario | H147: Ambiental (Principal) | I147: — | K147: Apoyo ambiental / gestión del riesgo / seguridad marítima
A148: Mesas Rurales | B148: Tierra bomba | C148: Dependencia | D148: EPA Cartagena | E148: Descentralizado | F148: Público | G148: Secundario | H148: Ambiental (Principal) | I148: — | J148: Dependencia distrital ya registrada en la matriz. | K148: Apoyo ambiental / gestión del riesgo / seguridad marítima
...

Sheet Cobertura de actores
A1: Código | B1: Actor / dependencia | C1: Tipo | D1: Dimensiones (condición) | E1: Eje transversal Crisis | F1: N° de mesas donde participa | G1: Estado
A2: Dependencia | B2: Alcaldías Locales 1, 2 y 3 | C2: Territorial | D2: Comunitaria (Principal); Personal (Secundario) | E2: Secundario | F2: =COUNTIF('Detalle por mesa'!$D:$D,B2) -> 26 | G2: =IF(F2=0,"Sin mesa","Cubierto") -> Cubierto
A3: Dependencia | B3: CARDIQUE | C3: Descentralizado | D3: Ambiental (Principal) | E3: — | F3: =COUNTIF('Detalle por mesa'!$D:$D,B3) -> 13 | G3: =IF(F3=0,"Sin mesa","Cubierto") -> Cubierto
A4: Dependencia | B4: Corvivienda | C4: Descentralizado | D4: Económica (Principal); Ambiental (Principal) | E4: — | F4: =COUNTIF('Detalle por mesa'!$D:$D,B4) -> 3 | G4: =IF(F4=0,"Sin mesa","Cubierto") -> Cubierto
A5: Dependencia | B5: Cuerpo Oficial de Bomberos | C5: Oficina / Unidad asesora | D5: Personal (Secundario) | E5: Principal | F5: =COUNTIF('Detalle por mesa'!$D:$D,B5) -> 2 | G5: =IF(F5=0,"Sin mesa","Cubierto") -> Cubierto
A6: Dependencia | B6: Departamento Administrativo Distrital de Salud (DADIS) | C6: Descentralizado | D6: Alimentaria (Secundario); Salud y sanitaria (Principal) | E6: — | F6: =COUNTIF('Detalle por mesa'!$D:$D,B6) -> 6 | G6: =IF(F6=0,"Sin mesa","Cubierto") -> Cubierto
A7: Dependencia | B7: Departamento Administrativo de Tránsito y Transporte (DATT) | C7: Descentralizado | D7: Económica (Secundario); Personal (Principal) | E7: — | F7: =COUNTIF('Detalle por mesa'!$D:$D,B7) -> 5 | G7: =IF(F7=0,"Sin mesa","Cubierto") -> Cubierto
A8: Dependencia | B8: Distriseguridad | C8: Descentralizado | D8: Personal (Principal) | E8: Secundario | F8: =COUNTIF('Detalle por mesa'!$D:$D,B8) -> 2 | G8: =IF(F8=0,"Sin mesa","Cubierto") -> Cubierto
A9: Dependencia | B9: EPA Cartagena | C9: Descentralizado | D9: Ambiental (Principal) | E9: — | F9: =COUNTIF('Detalle por mesa'!$D:$D,B9) -> 13 | G9: =IF(F9=0,"Sin mesa","Cubierto") -> Cubierto
A10: Dependencia | B10: Escuela Taller de Cartagena de Indias (ETCAR) | C10: Descentralizado | D10: Comunitaria (Secundario); Económica (Principal) | E10: — | F10: =COUNTIF('Detalle por mesa'!$D:$D,B10) -> 4 | G10: =IF(F10=0,"Sin mesa","Cubierto") -> Cubierto
A11: Dependencia | B11: Escuela de Gobierno y Liderazgo | C11: Oficina / Unidad asesora | D11: Comunitaria (Principal); Política (Secundario) | E11: — | F11: =COUNTIF('Detalle por mesa'!$D:$D,B11) -> 3 | G11: =IF(F11=0,"Sin mesa","Cubierto") -> Cubierto
A12: Dependencia | B12: Gerencia de Espacio Público y Movilidad (GEPM) | C12: Gerencia | D12: Comunitaria (Secundario); Económica (Principal); Personal (Secundario) | E12: — | F12: =COUNTIF('Detalle por mesa'!$D:$D,B12) -> 5 | G12: =IF(F12=0,"Sin mesa","Cubierto") -> Cubierto
A13: Dependencia | B13: Institución Universitaria Mayor de Cartagena (Colmayor) | C13: Empresa / Educación | D13: Comunitaria (Secundario); Económica (Principal) | E13: — | F13: =COUNTIF('Detalle por mesa'!$D:$D,B13) -> 4 | G13: =IF(F13=0,"Sin mesa","Cubierto") -> Cubierto
... A110: SOC-07 | B110: Fundación Ecovida | C110: Sector Social | D110: Comunitaria (Secundario); Ambiental (Principal) | E110: — | F110: =COUNTIF('Detalle por mesa'!$D:$D,B110) -> 14 | G110: =IF(F110=0,"Sin mesa","Cubierto") -> Cubierto
B112: Actores únicos de la matriz | F112: =COUNTA(B2:B110) -> 109
B113: Actores sin mesa | F113: =COUNTIF(G2:G110,"Sin mesa") -> 0

Sheet Notas
A1: NOTAS Y SUPUESTOS
A3: 1. Estructura
A4: Se mantiene la estructura del archivo original (clasificaciones Territoriales, Rurales, Poblacionales y Sectoriales; columnas Dirección, Fecha y Hora) y se agregan columnas resumen (dimensión, totales, actores clave). El detalle completo por mesa está en la hoja "Detalle por mesa".
A5: El original tenía 33 mesas (3 + 11 + 8 + 11). Esta versión tiene 35 (3 + 11 + 9 + 12). Se retiró el asterisco de los nombres de las mesas rurales para que las fórmulas de conteo funcionen.
A7: 2. Las dos mesas nuevas (propuesta — confirmar o reemplazar)
A8: Mesa Poblacional "Migrantes y refugiados": la matriz tiene un grupo claro de actores sobre migración (AVEC, Fundación Colombia Somos Todos, OIM, ACNUR, Migración Colombia) sin mesa poblacional equivalente.
A9: Mesa Sectorial "Seguridad alimentaria": la dimensión Alimentaria era la única de las 7 dimensiones sin mesa propia. Tiene solo 5 actores en la matriz (SED/PAE, SPD/UMATA, DADIS, PES-PR e ICBF), por eso es la mesa más pequeña.
A11: 3. Cómo se asignaron los actores
A12: Marco de seguridad humana: las 7 dimensiones son Comunitaria, Económica, Personal, Política, Alimentaria, Ambiental y Salud y sanitaria. La hoja CRISIS de la matriz se trata como eje transversal (fuera de las 7): sus actores conservan la marca en la columna "Eje transversal Crisis" y cada mesa muestra cuántos tiene. Ningún actor de Crisis se pierde, porque todos aparecen también en alguna de las 7 dimensiones.
A13: Cada mesa indica la dimensión principal a la que responde y otras dimensiones complementarias (propuesta del análisis, validar). Las 7 dimensiones tienen al menos una mesa como principal.
A14: Mesas sectoriales ligadas a una dimensión (Salud, Seguridad y Convivencia, Desarrollo económico, Transparencia, Seguridad alimentaria, Medio ambiente): se incluyen todos los actores de la hoja de esa dimensión, con la condición Principal/Secundaria que tienen allí. La mesa de Medio ambiente, Gestión del riesgo y Planeación incorpora además los actores de Crisis (gestión del riesgo) por el nombre de la mesa.
A15: Resto de mesas (territoriales, rurales, poblacionales y el resto de sectoriales): asignación por temática, usando el aporte y las articulaciones declaradas en la matriz. Principal = actor central del tema; Secundario = apoyo o articulación. La asignación por localidad y por corregimiento es una propuesta del análisis (la matriz solo habla de "Alcaldías Locales 1, 2 y 3"); validar.
... A34: Se agregó la hoja "Proyección ±500" con tres escenarios: mínimo 2.000, central 2.500 y máximo 3.000. Las metas de bloque se escalan ×0,8 y ×1,2 y se reparten con el mismo método (pisos y pesos); el margen es editable en la celda C6 de esa hoja. En la hoja "Mesas" se añadieron las columnas "Meta mínima (−500)" y "Meta máxima (+500)".
